FPGA/Experiment_5/fir_filter_pipeline.v


// Experiment 5:
 
// Mannava Venkatasai 
// EE24MTECH12008
// FIR filter Design using pipe lining
// input is in Q14 format


`timescale 1ns/1ps
module fir_filter( 
    input wire clk, 
    input rst, 
    input signed [15:0] input_signal,  
    output reg signed[15:0] output_signal  
); 

parameter N = 123;   

reg signed [15:0]filter_coefcients[0:N-1]; 
reg signed [15:0]shift_reg[0:N-1]; 
reg signed [15:0]shift_reg_temp[0:N-1]; 
reg signed [31:0]mul_reg[0:N-1]; 


integer i;  
integer k;
integer count;
reg [31:0]d_out;
reg [31:0]acc;
reg [15:0]temp;

initial    
    begin  
        
        filter_coefcients[0] = -5;
        filter_coefcients[1] = -11;
        filter_coefcients[2] = -9;
        filter_coefcients[3] = 13;
        filter_coefcients[4] = 57;
        filter_coefcients[5] = 105;
        filter_coefcients[6] = 123;
        filter_coefcients[7] = 80;
        filter_coefcients[8] = -14;
        filter_coefcients[9] = -110;
        filter_coefcients[10] = -151;
        filter_coefcients[11] = -115;
        filter_coefcients[12] = -41;
        filter_coefcients[13] = 3;
        filter_coefcients[14] = -22;
        filter_coefcients[15] = -87;
        filter_coefcients[16] = -121;
        filter_coefcients[17] = -84;
        filter_coefcients[18] = -5;
        filter_coefcients[19] = 43;
        filter_coefcients[20] = 15;
        filter_coefcients[21] = -53;
        filter_coefcients[22] = -77;
        filter_coefcients[23] = -13;
        filter_coefcients[24] = 91;
        filter_coefcients[25] = 140;
        filter_coefcients[26] = 90;
        filter_coefcients[27] = 3;
        filter_coefcients[28] = -11;
        filter_coefcients[29] = 87;
        filter_coefcients[30] = 213;
        filter_coefcients[31] = 242;
        filter_coefcients[32] = 141;
        filter_coefcients[33] = 15;
        filter_coefcients[34] = 6;
        filter_coefcients[35] = 137;
        filter_coefcients[36] = 273;
        filter_coefcients[37] = 249;
        filter_coefcients[38] = 59;
        filter_coefcients[39] = -124;
        filter_coefcients[40] = -119;
        filter_coefcients[41] = 63;
        filter_coefcients[42] = 201;
        filter_coefcients[43] = 90;
        filter_coefcients[44] = -227;
        filter_coefcients[45] = -469;
        filter_coefcients[46] = -404;
        filter_coefcients[47] = -114;
        filter_coefcients[48] = 42;
        filter_coefcients[49] = -204;
        filter_coefcients[50] = -710;
        filter_coefcients[51] = -1002;
        filter_coefcients[52] = -751;
        filter_coefcients[53] = -180;
        filter_coefcients[54] = 58;
        filter_coefcients[55] = -493;
        filter_coefcients[56] = -1507;
        filter_coefcients[57] = -1972;
        filter_coefcients[58] = -991;
        filter_coefcients[59] = 1341;
        filter_coefcients[60] = 3799;
        filter_coefcients[61] = 4849;
        filter_coefcients[62] = 3799;
        filter_coefcients[63] = 1341;
        filter_coefcients[64] = -991;
        filter_coefcients[65] = -1972;
        filter_coefcients[66] = -1507;
        filter_coefcients[67] = -493;
        filter_coefcients[68] = 58;
        filter_coefcients[69] = -180;
        filter_coefcients[70] = -751;
        filter_coefcients[71] = -1002;
        filter_coefcients[72] = -710;
        filter_coefcients[73] = -204;
        filter_coefcients[74] = 42;
        filter_coefcients[75] = -114;
        filter_coefcients[76] = -404;
        filter_coefcients[77] = -469;
        filter_coefcients[78] = -227;
        filter_coefcients[79] = 90;
        filter_coefcients[80] = 201;
        filter_coefcients[81] = 63;
        filter_coefcients[82] = -119;
        filter_coefcients[83] = -124;
        filter_coefcients[84] = 59;
        filter_coefcients[85] = 249;
        filter_coefcients[86] = 273;
        filter_coefcients[87] = 137;
        filter_coefcients[88] = 6;
        filter_coefcients[89] = 15;
        filter_coefcients[90] = 141;
        filter_coefcients[91] = 242;
        filter_coefcients[92] = 213;
        filter_coefcients[93] = 87;
        filter_coefcients[94] = -11;
        filter_coefcients[95] = 3;
        filter_coefcients[96] = 90;
        filter_coefcients[97] = 140;
        filter_coefcients[98] = 91;
        filter_coefcients[99] = -13;
        filter_coefcients[100] = -77;
        filter_coefcients[101] = -53;
        filter_coefcients[102] = 15;
        filter_coefcients[103] = 43;
        filter_coefcients[104] = -5;
        filter_coefcients[105] = -84;
        filter_coefcients[106] = -121;
        filter_coefcients[107] = -87;
        filter_coefcients[108] = -22;
        filter_coefcients[109] = 3;
        filter_coefcients[110] = -41;
        filter_coefcients[111] = -115;
        filter_coefcients[112] = -151;
        filter_coefcients[113] = -110;
        filter_coefcients[114] = -14;
        filter_coefcients[115] = 80;
        filter_coefcients[116] = 123;
        filter_coefcients[117] = 105;
        filter_coefcients[118] = 57;
        filter_coefcients[119] = 13;
        filter_coefcients[120] = -9;
        filter_coefcients[121] = -11;
        filter_coefcients[122] = -5;

        for(i=0;i<N;i=i+1)
        begin
            shift_reg[i] = 0;
        end
        count = 0;
    end

    always @ (posedge clk)
    begin
        if(rst)
        begin

            d_out = 0;

        end
        else
        begin

        for(i = N-1;i>0;i=i-1)
        begin
            shift_reg[i] <= shift_reg[i-1];
        end
        shift_reg_temp[0] <= shift_reg[0];
        if(count < N)
        begin
        shift_reg[0] <= input_signal;
        count <= count + 16'd1;
        end
        else
        begin
             shift_reg[0] <= 16'b0;
        end

        // $display("input_signal = %d",input_signal);
        // $display("time = %t rst = %d shift_reg = [%d%d%d%d%d]", $time ,shift_reg[0], shift_reg[1], shift_reg[2], shift_reg[3], shift_reg[4],rst);
        
        acc = 0;
        for(i = 0;i<N;i=i+1)
        begin
            // $display("time = %t shift_reg[%d] = %d ,acc = %d",$time,i,shift_reg[i],acc);
            mul_reg[i]  <= (shift_reg[i] * filter_coefcients[i])>>14;
        end

        for(i = 0;i<N;i=i+1)
        begin
            // $display("time = %t shift_reg[%d] = %d ,acc = %d",$time,i,shift_reg[i],acc);
            acc  = acc + mul_reg[i];
        end

        output_signal <= acc;

        
        end



    end

        

       

endmodule

FPGA/Experiment_5/fir_filter_pipeline_tb.v

// Experiment 5:
 
// Mannava Venkatasai 
// EE24MTECH12008
// FIR filter Design with pipeline

`timescale 1ns/1ps
module fir_filter_tb;

reg clk;
reg rst;
reg signed [15:0] x;
wire signed [15:0] y;
integer i;
integer f1,read_status;

reg signed [15:0] f_input;

parameter N = 123; 

fir_filter filter(
    .clk(clk),
    .rst(rst),
    .input_signal(x),
    .output_signal(y)
);

initial 
begin
    clk = 0;
    forever #5 clk = ~clk;
    
end

initial begin
    $dumpfile("wave.vcd");
    $dumpvars(0, fir_filter_tb);
    f1 = $fopen("input_signal_1.txt", "r");  

    rst = 1;
    #15;
    rst = 0;

    for (i = 1; i <= 2400 + N -1 + 3; i++) 
    begin
        read_status = $fscanf(f1, "%d\n", f_input);  
        x = f_input;
        // $display("\ntime = %t input = %d, rst = %d, out = %d", $time, x, rst, y);
        $display("%d",y);
        #10;
    end

    #10;
    $finish;
end

endmodule

FPGA/Experiment_5/wave.vcd
$date
	Fri Mar 28 21:19:26 2025
$end
$version
	Icarus Verilog
$end
$timescale
	1ps
$end
$scope module fir_filter_tb $end
$var wire 16 ! y [15:0] $end
$var reg 1 " clk $end
$var reg 16 # f_input [15:0] $end
$var reg 1 $ rst $end
$var reg 16 % x [15:0] $end
$var integer 32 & f1 [31:0] $end
$var integer 32 ' i [31:0] $end
$var integer 32 ( read_status [31:0] $end
$scope module filter $end
$var wire 1 " clk $end
$var wire 16 ) input_signal [15:0] $end
$var wire 1 $ rst $end
$var reg 32 * acc [31:0] $end
$var reg 32 + d_out [31:0] $end
$var reg 16 , output_signal [15:0] $end
$var integer 32 - count [31:0] $end
$var integer 32 . i [31:0] $end
$upscope $end
$upscope $end
$enddefinitions $end
#0
$dumpvars
b1111011 .
b0 -
bx ,
bx +
bx *
bx )
bx (
bx '
b10000000000000000000000000000011 &
bx %
1$
bx #
0"
bx !
$end
#5000
b0 +
1"
#10000
0"
#15000
b1 -
bx *
b1111011 .
1"
b0 %
b0 )
b1 (
b0 #
b1 '
0$
#20000
0"
#25000
b0 !
b0 ,
b10 -
b0 *
b1111011 .
1"
b11010110 %
b11010110 )
b11010110 #
b10 '
#30000
0"
#35000
b11 -
b1111011 .
1"
b110101101 %
b110101101 )
b110101101 #
b11 '
#40000
0"
#45000
b1111111111111111 !
b1111111111111111 ,
b100 -
b111111111111111111 *
b1111011 .
1"
b1010000011 %
b1010000011 )
b1010000011 #
b100 '
#50000
0"
#55000
b1111111111111110 !
b1111111111111110 ,
b101 -
b1111111111111111110 *
b1111011 .
1"
b1101011001 %
b1101011001 )
b1101011001 #
b101 '
#60000
0"
#65000
b1111111111111101 !
b1111111111111101 ,
b110 -
b10111111111111111101 *
b1111011 .
1"
b10000110000 %
b10000110000 )
b10000110000 #
b110 '
#70000
0"
#75000
b111 -
b10111111111111111101 *
b1111011 .
1"
b10100000101 %
b10100000101 )
b10100000101 #
b111 '
#80000
0"
#85000
b1000 -
b10111111111111111101 *
b1111011 .
1"
b10111011011 %
b10111011011 )
b10111011011 #
b1000 '
#90000
0"
#95000
b1111111111111111 !
b1111111111111111 ,
b1001 -
b10111111111111111111 *
b1111011 .
1"
b11010110001 %
b11010110001 )
b11010110001 #
b1001 '
#100000
0"
#105000
b10 !
b10 ,
b1010 -
b11000000000000000010 *
b1111011 .
1"
b11110000110 %
b11110000110 )
b11110000110 #
b1010 '
#110000
0"
#115000
b110 !
b110 ,
b1011 -
b11000000000000000110 *
b1111011 .
1"
b100001011011 %
b100001011011 )
b100001011011 #
b1011 '
#120000
0"
#125000
b1010 !
b1010 ,
b1100 -
b100000000000000001010 *
b1111011 .
1"
b100100101111 %
b100100101111 )
b100100101111 #
b1100 '
#130000
0"
#135000
b1101 !
b1101 ,
b1101 -
b101000000000000001101 *
b1111011 .
1"
b101000000011 %
b101000000011 )
b101000000011 #
b1101 '
#140000
0"
#145000
b1111 !
b1111 ,
b1110 -
b110000000000000001111 *
b1111011 .
1"
b101011010111 %
b101011010111 )
b101011010111 #
b1110 '
#150000
0"
#155000
b1100 !
b1100 ,
b1111 -
b111000000000000001100 *
b1111011 .
1"
b101110101010 %
b101110101010 )
b101110101010 #
b1111 '
#160000
0"
#165000
b1011 !
b1011 ,
b10000 -
b1000000000000000001011 *
b1111011 .
1"
b110001111100 %
b110001111100 )
b110001111100 #
b10000 '
#170000
0"
#175000
b1001 !
b1001 ,
b10001 -
b1000000000000000001001 *
b1111011 .
1"
b110101001110 %
b110101001110 )
b110101001110 #
b10001 '
#180000
0"
#185000
b1000 !
b1000 ,
b10010 -
b1001000000000000001000 *
b1111011 .
1"
b111000100000 %
b111000100000 )
b111000100000 #
b10010 '
#190000
0"
#195000
b100 !
b100 ,
b10011 -
b1010000000000000000100 *
b1111011 .
1"
b111011110001 %
b111011110001 )
b111011110001 #
b10011 '
#200000
0"
#205000
b0 !
b0 ,
b10100 -
b1011000000000000000000 *
b1111011 .
1"
b111111000001 %
b111111000001 )
b111111000001 #
b10100 '
#210000
0"
#215000
b1111111111111010 !
b1111111111111010 ,
b10101 -
b1011111111111111111010 *
b1111011 .
1"
b1000010010000 %
b1000010010000 )
b1000010010000 #
b10101 '
#220000
0"
#225000
b1111111111110100 !
b1111111111110100 ,
b10110 -
b1100111111111111110100 *
b1111011 .
1"
b1000101011111 %
b1000101011111 )
b1000101011111 #
b10110 '
#230000
0"
#235000
b1111111111101110 !
b1111111111101110 ,
b10111 -
b1100111111111111101110 *
b1111011 .
1"
b1001000101101 %
b1001000101101 )
b1001000101101 #
b10111 '
#240000
0"
#245000
b1111111111101010 !
b1111111111101010 ,
b11000 -
b1100111111111111101010 *
b1111011 .
1"
b1001011111011 %
b1001011111011 )
b1001011111011 #
b11000 '
#250000
0"
#255000
b1111111111100110 !
b1111111111100110 ,
b11001 -
b1101111111111111100110 *
b1111011 .
1"
b1001111000111 %
b1001111000111 )
b1001111000111 #
b11001 '
#260000
0"
#265000
b1111111111011110 !
b1111111111011110 ,
b11010 -
b1110111111111111011110 *
b1111011 .
1"
b1010010010010 %
b1010010010010 )
b1010010010010 #
b11010 '
#270000
0"
#275000
b1111111111010101 !
b1111111111010101 ,
b11011 -
b1111111111111111010101 *
b1111011 .
1"
b1010101011101 %
b1010101011101 )
b1010101011101 #
b11011 '
#280000
0"
#285000
b1111111111010010 !
b1111111111010010 ,
b11100 -
b1111111111111111010010 *
b1111011 .
1"
b1011000100111 %
b1011000100111 )
b1011000100111 #
b11100 '
#290000
0"
#295000
b1111111111001101 !
b1111111111001101 ,
b11101 -
b1111111111111111001101 *
b1111011 .
1"
b1011011110000 %
b1011011110000 )
b1011011110000 #
b11101 '
#300000
0"
#305000
b11110 -
b1111111111111111001101 *
b1111011 .
1"
b1011110110111 %
b1011110110111 )
b1011110110111 #
b11110 '
#310000
0"
#315000
b1111111111001001 !
b1111111111001001 ,
b11111 -
b1111111111111111001001 *
b1111011 .
1"
b1100001111110 %
b1100001111110 )
b1100001111110 #
b11111 '
#320000
0"
#325000
b1111111111000101 !
b1111111111000101 ,
b100000 -
b10000111111111111000101 *
b1111011 .
1"
b1100101000011 %
b1100101000011 )
b1100101000011 #
b100000 '
#330000
0"
#335000
b100001 -
b10000111111111111000101 *
b1111011 .
1"
b1101000001000 %
b1101000001000 )
b1101000001000 #
b100001 '
#340000
0"
#345000
b100010 -
b10000111111111111000101 *
b1111011 .
1"
b1101011001011 %
b1101011001011 )
b1101011001011 #
b100010 '
#350000
0"
#355000
b1111111111001010 !
b1111111111001010 ,
b100011 -
b10000111111111111001010 *
b1111011 .
1"
b1101110001101 %
b1101110001101 )
b1101110001101 #
b100011 '
#360000
0"
#365000
b1111111111010000 !
b1111111111010000 ,
b100100 -
b10000111111111111010000 *
b1111011 .
1"
b1110001001110 %
b1110001001110 )
b1110001001110 #
b100100 '
#370000
0"
#375000
b1111111111010111 !
b1111111111010111 ,
b100101 -
b10000111111111111010111 *
b1111011 .
1"
b1110100001110 %
b1110100001110 )
b1110100001110 #
b100101 '
#380000
0"
#385000
b1111111111011101 !
b1111111111011101 ,
b100110 -
b10000111111111111011101 *
b1111011 .
1"
b1110111001101 %
b1110111001101 )
b1110111001101 #
b100110 '
#390000
0"
#395000
b1111111111100101 !
b1111111111100101 ,
b100111 -
b10000111111111111100101 *
b1111011 .
1"
b1111010001010 %
b1111010001010 )
b1111010001010 #
b100111 '
#400000
0"
#405000
b1111111111110000 !
b1111111111110000 ,
b101000 -
b10000111111111111110000 *
b1111011 .
1"
b1111101000110 %
b1111101000110 )
b1111101000110 #
b101000 '
#410000
0"
#415000
b10 !
b10 ,
b101001 -
b10001000000000000000010 *
b1111011 .
1"
b10000000000000 %
b10000000000000 )
b10000000000000 #
b101001 '
#420000
0"
#425000
b10011 !
b10011 ,
b101010 -
b10001000000000000010011 *
b1111011 .
1"
b10000010111001 %
b10000010111001 )
b10000010111001 #
b101010 '
#430000
0"
#435000
b100000 !
b100000 ,
b101011 -
b10010000000000000100000 *
b1111011 .
1"
b10000101110001 %
b10000101110001 )
b10000101110001 #
b101011 '
#440000
0"
#445000
b101111 !
b101111 ,
b101100 -
b10011000000000000101111 *
b1111011 .
1"
b10001000100111 %
b10001000100111 )
b10001000100111 #
b101100 '
#450000
0"
#455000
b111001 !
b111001 ,
b101101 -
b10011000000000000111001 *
b1111011 .
1"
b10001011011011 %
b10001011011011 )
b10001011011011 #
b101101 '
#460000
0"
#465000
b1001000 !
b1001000 ,
b101110 -
b10011000000000001001000 *
b1111011 .
1"
b10001110001110 %
b10001110001110 )
b10001110001110 #
b101110 '
#470000
0"
#475000
b1011011 !
b1011011 ,
b101111 -
b10011000000000001011011 *
b1111011 .
1"
b10010001000000 %
b10010001000000 )
b10010001000000 #
b101111 '
#480000
0"
#485000
b1101111 !
b1101111 ,
b110000 -
b10100000000000001101111 *
b1111011 .
1"
b10010011110000 %
b10010011110000 )
b10010011110000 #
b110000 '
#490000
0"
#495000
b1110011 !
b1110011 ,
b110001 -
b10101000000000001110011 *
b1111011 .
1"
b10010110011110 %
b10010110011110 )
b10010110011110 #
b110001 '
#500000
0"
#505000
b1110111 !
b1110111 ,
b110010 -
b10110000000000001110111 *
b1111011 .
1"
b10011001001011 %
b10011001001011 )
b10011001001011 #
b110010 '
#510000
0"
#515000
b110011 -
b10111000000000001110111 *
b1111011 .
1"
b10011011110110 %
b10011011110110 )
b10011011110110 #
b110011 '
#520000
0"
#525000
b1111101 !
b1111101 ,
b110100 -
b10111000000000001111101 *
b1111011 .
1"
b10011110011111 %
b10011110011111 )
b10011110011111 #
b110100 '
#530000
0"
#535000
b1110110 !
b1110110 ,
b110101 -
b11000000000000001110110 *
b1111011 .
1"
b10100001000111 %
b10100001000111 )
b10100001000111 #
b110101 '
#540000
0"
#545000
b1101001 !
b1101001 ,
b110110 -
b11001000000000001101001 *
b1111011 .
1"
b10100011101101 %
b10100011101101 )
b10100011101101 #
b110110 '
#550000
0"
#555000
b1011000 !
b1011000 ,
b110111 -
b11010000000000001011000 *
b1111011 .
1"
b10100110010001 %
b10100110010001 )
b10100110010001 #
b110111 '
#560000
0"
#565000
b110110 !
b110110 ,
b111000 -
b11011000000000000110110 *
b1111011 .
1"
b10101000110011 %
b10101000110011 )
b10101000110011 #
b111000 '
#570000
0"
#575000
b1111 !
b1111 ,
b111001 -
b11100000000000000001111 *
b1111011 .
1"
b10101011010011 %
b10101011010011 )
b10101011010011 #
b111001 '
#580000
0"
#585000
b1111111111110001 !
b1111111111110001 ,
b111010 -
b11011111111111111110001 *
b1111011 .
1"
b10101101110001 %
b10101101110001 )
b10101101110001 #
b111010 '
#590000
0"
#595000
b1111111111000111 !
b1111111111000111 ,
b111011 -
b11100111111111111000111 *
b1111011 .
1"
b10110000001110 %
b10110000001110 )
b10110000001110 #
b111011 '
#600000
0"
#605000
b1111111110001011 !
b1111111110001011 ,
b111100 -
b11101111111111110001011 *
b1111011 .
1"
b10110010101001 %
b10110010101001 )
b10110010101001 #
b111100 '
#610000
0"
#615000
b1111111100110110 !
b1111111100110110 ,
b111101 -
b11110111111111100110110 *
b1111011 .
1"
b10110101000001 %
b10110101000001 )
b10110101000001 #
b111101 '
#620000
0"
#625000
b1111111011010000 !
b1111111011010000 ,
b111110 -
b11111111111111011010000 *
b1111011 .
1"
b10110111011000 %
b10110111011000 )
b10110111011000 #
b111110 '
#630000
0"
#635000
b1111111001111110 !
b1111111001111110 ,
b111111 -
b11111111111111001111110 *
b1111011 .
1"
b10111001101101 %
b10111001101101 )
b10111001101101 #
b111111 '
#640000
0"
#645000
b1111111001011111 !
b1111111001011111 ,
b1000000 -
b11111111111111001011111 *
b1111011 .
1"
b10111011111111 %
b10111011111111 )
b10111011111111 #
b1000000 '
#650000
0"
#655000
b1111111001111110 !
b1111111001111110 ,
b1000001 -
b11111111111111001111110 *
b1111011 .
1"
b10111110010000 %
b10111110010000 )
b10111110010000 #
b1000001 '
#660000
0"
#665000
b1111111011001111 !
b1111111011001111 ,
b1000010 -
b11111111111111011001111 *
b1111011 .
1"
b11000000011110 %
b11000000011110 )
b11000000011110 #
b1000010 '
#670000
0"
#675000
b1111111100110000 !
b1111111100110000 ,
b1000011 -
b11111111111111100110000 *
b1111011 .
1"
b11000010101010 %
b11000010101010 )
b11000010101010 #
b1000011 '
#680000
0"
#685000
b1111111110001001 !
b1111111110001001 ,
b1000100 -
b100000111111111110001001 *
b1111011 .
1"
b11000100110101 %
b11000100110101 )
b11000100110101 #
b1000100 '
#690000
0"
#695000
b1111111111000110 !
b1111111111000110 ,
b1000101 -
b100001111111111111000110 *
b1111011 .
1"
b11000110111101 %
b11000110111101 )
b11000110111101 #
b1000101 '
#700000
0"
#705000
b1111111111101011 !
b1111111111101011 ,
b1000110 -
b100010111111111111101011 *
b1111011 .
1"
b11001001000011 %
b11001001000011 )
b11001001000011 #
b1000110 '
#710000
0"
#715000
b1011 !
b1011 ,
b1000111 -
b100100000000000000001011 *
b1111011 .
1"
b11001011000110 %
b11001011000110 )
b11001011000110 #
b1000111 '
#720000
0"
#725000
b110010 !
b110010 ,
b1001000 -
b100100000000000000110010 *
b1111011 .
1"
b11001101001000 %
b11001101001000 )
b11001101001000 #
b1001000 '
#730000
0"
#735000
b1010001 !
b1010001 ,
b1001001 -
b100101000000000001010001 *
b1111011 .
1"
b11001111000111 %
b11001111000111 )
b11001111000111 #
b1001001 '
#740000
0"
#745000
b1101001 !
b1101001 ,
b1001010 -
b100110000000000001101001 *
b1111011 .
1"
b11010001000100 %
b11010001000100 )
b11010001000100 #
b1001010 '
#750000
0"
#755000
b1101110 !
b1101110 ,
b1001011 -
b100111000000000001101110 *
b1111011 .
1"
b11010010111110 %
b11010010111110 )
b11010010111110 #
b1001011 '
#760000
0"
#765000
b1001100 -
b101000000000000001101110 *
b1111011 .
1"
b11010100110111 %
b11010100110111 )
b11010100110111 #
b1001100 '
#770000
0"
#775000
b1101100 !
b1101100 ,
b1001101 -
b101001000000000001101100 *
b1111011 .
1"
b11010110101101 %
b11010110101101 )
b11010110101101 #
b1001101 '
#780000
0"
#785000
b1100111 !
b1100111 ,
b1001110 -
b101001000000000001100111 *
b1111011 .
1"
b11011000100000 %
b11011000100000 )
b11011000100000 #
b1001110 '
#790000
0"
#795000
b1001111 -
b101010000000000001100111 *
b1111011 .
1"
b11011010010010 %
b11011010010010 )
b11011010010010 #
b1001111 '
#800000
0"
#805000
b1011100 !
b1011100 ,
b1010000 -
b101011000000000001011100 *
b1111011 .
1"
b11011100000001 %
b11011100000001 )
b11011100000001 #
b1010000 '
#810000
0"
#815000
b1001111 !
b1001111 ,
b1010001 -
b101100000000000001001111 *
b1111011 .
1"
b11011101101101 %
b11011101101101 )
b11011101101101 #
b1010001 '
#820000
0"
#825000
b111100 !
b111100 ,
b1010010 -
b101101000000000000111100 *
b1111011 .
1"
b11011111010111 %
b11011111010111 )
b11011111010111 #
b1010010 '
#830000
0"
#835000
b100111 !
b100111 ,
b1010011 -
b101101000000000000100111 *
b1111011 .
1"
b11100000111111 %
b11100000111111 )
b11100000111111 #
b1010011 '
#840000
0"
#845000
b11111 !
b11111 ,
b1010100 -
b101101000000000000011111 *
b1111011 .
1"
b11100010100100 %
b11100010100100 )
b11100010100100 #
b1010100 '
#850000
0"
#855000
b1100 !
b1100 ,
b1010101 -
b101101000000000000001100 *
b1111011 .
1"
b11100100000110 %
b11100100000110 )
b11100100000110 #
b1010101 '
#860000
0"
#865000
b100 !
b100 ,
b1010110 -
b101110000000000000000100 *
b1111011 .
1"
b11100101100110 %
b11100101100110 )
b11100101100110 #
b1010110 '
#870000
0"
#875000
b1111111111101111 !
b1111111111101111 ,
b1010111 -
b101110111111111111101111 *
b1111011 .
1"
b11100111000100 %
b11100111000100 )
b11100111000100 #
b1010111 '
#880000
0"
#885000
b1111111111011110 !
b1111111111011110 ,
b1011000 -
b101110111111111111011110 *
b1111011 .
1"
b11101000011111 %
b11101000011111 )
b11101000011111 #
b1011000 '
#890000
0"
#895000
b1111111111010101 !
b1111111111010101 ,
b1011001 -
b101110111111111111010101 *
b1111011 .
1"
b11101001111000 %
b11101001111000 )
b11101001111000 #
b1011001 '
#900000
0"
#905000
b1111111111001001 !
b1111111111001001 ,
b1011010 -
b101110111111111111001001 *
b1111011 .
1"
b11101011001101 %
b11101011001101 )
b11101011001101 #
b1011010 '
#910000
0"
#915000
b1111111110111110 !
b1111111110111110 ,
b1011011 -
b101110111111111110111110 *
b1111011 .
1"
b11101100100001 %
b11101100100001 )
b11101100100001 #
b1011011 '
#920000
0"
#925000
b1111111110111000 !
b1111111110111000 ,
b1011100 -
b101110111111111110111000 *
b1111011 .
1"
b11101101110010 %
b11101101110010 )
b11101101110010 #
b1011100 '
#930000
0"
#935000
b1111111110110101 !
b1111111110110101 ,
b1011101 -
b101110111111111110110101 *
b1111011 .
1"
b11101111000000 %
b11101111000000 )
b11101111000000 #
b1011101 '
#940000
0"
#945000
b1111111110101101 !
b1111111110101101 ,
b1011110 -
b101110111111111110101101 *
b1111011 .
1"
b11110000001011 %
b11110000001011 )
b11110000001011 #
b1011110 '
#950000
0"
#955000
b1111111110101000 !
b1111111110101000 ,
b1011111 -
b101110111111111110101000 *
b1111011 .
1"
b11110001010100 %
b11110001010100 )
b11110001010100 #
b1011111 '
#960000
0"
#965000
b1111111110101001 !
b1111111110101001 ,
b1100000 -
b101110111111111110101001 *
b1111011 .
1"
b11110010011011 %
b11110010011011 )
b11110010011011 #
b1100000 '
#970000
0"
#975000
b1111111110101000 !
b1111111110101000 ,
b1100001 -
b101110111111111110101000 *
b1111011 .
1"
b11110011011110 %
b11110011011110 )
b11110011011110 #
b1100001 '
#980000
0"
#985000
b1111111110110000 !
b1111111110110000 ,
b1100010 -
b101111111111111110110000 *
b1111011 .
1"
b11110100011111 %
b11110100011111 )
b11110100011111 #
b1100010 '
#990000
0"
#995000
b1111111110101110 !
b1111111110101110 ,
b1100011 -
b101111111111111110101110 *
b1111011 .
1"
b11110101011101 %
b11110101011101 )
b11110101011101 #
b1100011 '
#1000000
0"
#1005000
b1111111110110100 !
b1111111110110100 ,
b1100100 -
b101111111111111110110100 *
b1111011 .
1"
b11110110011001 %
b11110110011001 )
b11110110011001 #
b1100100 '
#1010000
0"
#1015000
b1111111110110111 !
b1111111110110111 ,
b1100101 -
b101111111111111110110111 *
b1111011 .
1"
b11110111010010 %
b11110111010010 )
b11110111010010 #
b1100101 '
#1020000
0"
#1025000
b1111111110111101 !
b1111111110111101 ,
b1100110 -
b101111111111111110111101 *
b1111011 .
1"
b11111000001000 %
b11111000001000 )
b11111000001000 #
b1100110 '
#1030000
0"
#1035000
b1111111111000100 !
b1111111111000100 ,
b1100111 -
b110000111111111111000100 *
b1111011 .
1"
b11111000111011 %
b11111000111011 )
b11111000111011 #
b1100111 '
#1040000
0"
#1045000
b1111111111000110 !
b1111111111000110 ,
b1101000 -
b110001111111111111000110 *
b1111011 .
1"
b11111001101100 %
b11111001101100 )
b11111001101100 #
b1101000 '
#1050000
0"
#1055000
b1111111111001010 !
b1111111111001010 ,
b1101001 -
b110010111111111111001010 *
b1111011 .
1"
b11111010011010 %
b11111010011010 )
b11111010011010 #
b1101001 '
#1060000
0"
#1065000
b1111111111001100 !
b1111111111001100 ,
b1101010 -
b110010111111111111001100 *
b1111011 .
1"
b11111011000101 %
b11111011000101 )
b11111011000101 #
b1101010 '
#1070000
0"
#1075000
b1111111111010100 !
b1111111111010100 ,
b1101011 -
b110010111111111111010100 *
b1111011 .
1"
b11111011101110 %
b11111011101110 )
b11111011101110 #
b1101011 '
#1080000
0"
#1085000
b1111111111011001 !
b1111111111011001 ,
b1101100 -
b110011111111111111011001 *
b1111011 .
1"
b11111100010011 %
b11111100010011 )
b11111100010011 #
b1101100 '
#1090000
0"
#1095000
b1111111111011011 !
b1111111111011011 ,
b1101101 -
b110100111111111111011011 *
b1111011 .
1"
b11111100110110 %
b11111100110110 )
b11111100110110 #
b1101101 '
#1100000
0"
#1105000
b1111111111100000 !
b1111111111100000 ,
b1101110 -
b110101111111111111100000 *
b1111011 .
1"
b11111101010110 %
b11111101010110 )
b11111101010110 #
b1101110 '
#1110000
0"
#1115000
b1111111111011100 !
b1111111111011100 ,
b1101111 -
b110110111111111111011100 *
b1111011 .
1"
b11111101110100 %
b11111101110100 )
b11111101110100 #
b1101111 '
#1120000
0"
#1125000
b1110000 -
b110111111111111111011100 *
b1111011 .
1"
b11111110001110 %
b11111110001110 )
b11111110001110 #
b1110000 '
#1130000
0"
#1135000
b1111111111100000 !
b1111111111100000 ,
b1110001 -
b110111111111111111100000 *
b1111011 .
1"
b11111110100110 %
b11111110100110 )
b11111110100110 #
b1110001 '
#1140000
0"
#1145000
b1111111111100100 !
b1111111111100100 ,
b1110010 -
b111000111111111111100100 *
b1111011 .
1"
b11111110111011 %
b11111110111011 )
b11111110111011 #
b1110010 '
#1150000
0"
#1155000
b1111111111011111 !
b1111111111011111 ,
b1110011 -
b111001111111111111011111 *
b1111011 .
1"
b11111111001101 %
b11111111001101 )
b11111111001101 #
b1110011 '
#1160000
0"
#1165000
b1111111111011010 !
b1111111111011010 ,
b1110100 -
b111010111111111111011010 *
b1111011 .
1"
b11111111011101 %
b11111111011101 )
b11111111011101 #
b1110100 '
#1170000
0"
#1175000
b1111111111011011 !
b1111111111011011 ,
b1110101 -
b111011111111111111011011 *
b1111011 .
1"
b11111111101010 %
b11111111101010 )
b11111111101010 #
b1110101 '
#1180000
0"
#1185000
b1111111111011000 !
b1111111111011000 ,
b1110110 -
b111100111111111111011000 *
b1111011 .
1"
b11111111110011 %
b11111111110011 )
b11111111110011 #
b1110110 '
#1190000
0"
#1195000
b1111111111010010 !
b1111111111010010 ,
b1110111 -
b111100111111111111010010 *
b1111011 .
1"
b11111111111010 %
b11111111111010 )
b11111111111010 #
b1110111 '
#1200000
0"
#1205000
b1111111111001011 !
b1111111111001011 ,
b1111000 -
b111100111111111111001011 *
b1111011 .
1"
b11111111111111 %
b11111111111111 )
b11111111111111 #
b1111000 '
#1210000
0"
#1215000
b1111001 -
b111100111111111111001011 *
b1111011 .
1"
b100000000000000 %
b100000000000000 )
b100000000000000 #
b1111001 '
#1220000
0"
#1225000
b1111111111001010 !
b1111111111001010 ,
b1111010 -
b111100111111111111001010 *
b1111011 .
1"
b11111111111111 %
b11111111111111 )
b11111111111111 #
b1111010 '
#1230000
0"
#1235000
b1111111111000111 !
b1111111111000111 ,
b1111011 -
b111100111111111111000111 *
b1111011 .
1"
b11111111111010 %
b11111111111010 )
b11111111111010 #
b1111011 '
#1240000
0"
#1245000
b1111111111001101 !
b1111111111001101 ,
b111101111111111111001101 *
b1111011 .
1"
b11111111110011 %
b11111111110011 )
b11111111110011 #
b1111100 '
#1250000
0"
#1255000
b1111111111001001 !
b1111111111001001 ,
b111110111111111111001001 *
b1111011 .
1"
b11111111101010 %
b11111111101010 )
b11111111101010 #
b1111101 '
#1260000
0"
