FPGA/Experiment_5/fir_filter_non_pipeline.v

`timescale 1ns/1ps
module fir_filter( 
    input wire clk, 
    input rst, 
    input signed [15:0] input_signal,  
    output reg signed[15:0] output_signal  
); 

parameter N = 5;   

reg signed [15:0]filter_coefcients[0:N-1]; 
reg signed [15:0]shift_reg[0:N-1]; 
integer i;  
integer k;
integer count;
reg [15:0]d_out;
reg [15:0]acc;
reg [15:0]temp;

initial    
    begin  
        filter_coefcients[0] = 1; 
        filter_coefcients[1] = 2;
        filter_coefcients[2] = 3; 
        filter_coefcients[3] = 4; 
        filter_coefcients[4] = 5; 

        shift_reg[0] = 0;
        shift_reg[1] = 0;
        shift_reg[2] = 0;
        shift_reg[3] = 0;
        shift_reg[4] = 0;
        count = 0;
    end

    always @ (posedge clk)
    begin
        if(rst)
        begin

            d_out = 0;

        end
        else
        begin

        for(i = N-1;i>0;i=i-1)
        begin
            shift_reg[i] <= shift_reg[i-1];
        end
        if(count < N)
        begin
        shift_reg[0] <= input_signal;
        count <= count + 16'd1;
        end
        else
        begin
             shift_reg[0] <= 16'b0;
        end

        // $display("input_signal = %d",input_signal);
        // $display("time = %t rst = %d shift_reg = [%d%d%d%d%d]", $time ,shift_reg[0], shift_reg[1], shift_reg[2], shift_reg[3], shift_reg[4],rst);
        
        acc = 0;
        for(i = 0;i<N;i=i+1)
        begin
            // $display("time = %t shift_reg[%d] = %d ,acc = %d",$time,i,shift_reg[i],acc);
            temp = shift_reg[i] * filter_coefcients[i];
            acc = acc + temp;
        end

        output_signal = acc;

        
        end



    end

        

       

endmodule

FPGA/Experiment_5/fir_filter_non_pipeline_tb.v
`timescale 1ns/1ps
module fir_filter_tb;

reg clk;
reg rst;
reg signed [15:0] x;
wire signed [15:0] y;



fir_filter filter(
    .clk(clk),
    .rst(rst),
    .input_signal(x),
    .output_signal(y)
);

initial 
begin
    clk = 0;
    forever #5 clk = ~clk;
    
end

initial
begin
    $dumpfile("wave.vcd");
    $dumpvars(0, fir_filter_tb);

    rst = 1;
    #15;

    rst = 0;


    x = 16'd1;
    $display("\ntime = %t input = %d,rst = %d ",$time,x,rst);
    
    #10;  
    x = 16'd2;
    $display("\ntime = %t input = %d,rst = %d ,out = %d",$time,x,rst,y);

    #10;  
    x = 16'd3;
    $display("\ntime = %t input = %d,rst = %d ,out = %d",$time,x,rst,y);

    #10;  
    x = 16'd4;
    $display("\ntime = %t input = %d,rst = %d out = %d",$time,x,rst,y);

    #10;  
    x = 16'd5;
    $display("\ntime = %t input = %d,rst = %d ,out = %d",$time,x,rst,y);

    #10;  
    x = 16'd5;
    $display("\ntime = %t input = %d,rst = %d ,out = %d",$time,x,rst,y);

    #10;  
    x = 16'd5;
    $display("\ntime = %t input = %d,rst = %d ,out = %d",$time,x,rst,y);

    #10;  
    x = 16'd5;
    $display("\ntime = %t input = %d,rst = %d ,out = %d",$time,x,rst,y);


    #10;  
    x = 16'd5;
    $display("\ntime = %t input = %d,rst = %d ,out = %d",$time,x,rst,y);


    #10;  
    x = 16'd5;
    $display("\ntime = %t input = %d,rst = %d ,out = %d",$time,x,rst,y);


    #10;  
    x = 16'd5;
    $display("\ntime = %t input = %d,rst = %d ,out = %d",$time,x,rst,y);

    #10;  

   
    #10;
    $finish;

end

endmodule

FPGA/Experiment_5/wave.vcd
$date
	Thu Mar 27 15:58:15 2025
$end
$version
	Icarus Verilog
$end
$timescale
	1ps
$end
$scope module fir_filter_tb $end
$var wire 16 ! y [15:0] $end
$var reg 1 " clk $end
$var reg 1 # rst $end
$var reg 16 $ x [15:0] $end
$scope module filter $end
$var wire 1 " clk $end
$var wire 16 % input_signal [15:0] $end
$var wire 1 # rst $end
$var reg 16 & acc [15:0] $end
$var reg 16 ' d_out [15:0] $end
$var reg 16 ( output_signal [15:0] $end
$var reg 16 ) temp [15:0] $end
$var integer 32 * count [31:0] $end
$var integer 32 + i [31:0] $end
$upscope $end
$upscope $end
$enddefinitions $end
#0
$dumpvars
bx +
b0 *
bx )
bx (
bx '
bx &
bx %
bx $
1#
0"
bx !
$end
#5000
b0 '
1"
#10000
0"
#15000
b1 *
b0 !
b0 (
b0 )
b0 &
b101 +
1"
b1 $
b1 %
0#
#20000
0"
#25000
b10 *
b1 !
b1 (
b1 &
b0 )
b101 +
1"
b10 $
b10 %
#30000
0"
#35000
b11 *
b100 !
b100 (
b0 )
b100 &
b101 +
1"
b11 $
b11 %
#40000
0"
#45000
b100 *
b1010 !
b1010 (
b0 )
b1010 &
b101 +
1"
b100 $
b100 %
#50000
0"
#55000
b101 *
b10100 !
b10100 (
b0 )
b10100 &
b101 +
1"
b101 $
b101 %
#60000
0"
#65000
b100011 !
b100011 (
b101 )
b100011 &
b101 +
1"
#70000
0"
#75000
b101100 !
b101100 (
b1010 )
b101100 &
b101 +
1"
#80000
0"
#85000
b101110 !
b101110 (
b1111 )
b101110 &
b101 +
1"
#90000
0"
#95000
b101000 !
b101000 (
b10100 )
b101000 &
b101 +
1"
#100000
0"
#105000
b11001 !
b11001 (
b11001 )
b11001 &
b101 +
1"
#110000
0"
#115000
b0 !
b0 (
b0 )
b0 &
b101 +
1"
#120000
0"
#125000
b101 +
1"
#130000
0"
#135000
b101 +
1"
