FPGA/Experiment_2/Experiment_2.v
/******************************************** Experiment 2 **************************************************

Perform basic fixed-point operations using Verilog on array of data (sum,
subtraction, multiplication and division) , write them to files and
verifiy using MATLAB reference


program.
Plot both outputs and show that both give same results.

Please use Q(2,14), Q(4,12) values from previous experiment as operand1 and operand2 
(store them in matlab as files and read them in Verilog). 
You need to take care of proper Q conversions. 
Also do only addition, subtraction and multiplications.
****************************************************************************************************************/


module fixed_point_arthematic(
input wire clk,
input signed [16:0] operand_1,
input signed [16:0] operand_2,
output reg signed [17:0] sum,
output reg signed [17:0] diff,
output reg signed [34:0] product
);


always @(posedge clk)
begin
    sum <= (operand_1 + (operand_2 << 2));
    diff <= (operand_1 - (operand_2 << 2));
    product <= (operand_1 * (operand_2 << 2)) >> 14;

end

endmodule

FPGA/Experiment_2/Experiment_2_tb.v
`timescale 10ns/1ps  // 1 time unit = 10 ns

module fixed_point_arthematic_tb;
    reg clk;
    reg signed [16:0] a,b;
    wire signed [17:0] sum,diff;
    wire signed [34:0] product;

    integer f1,f2,file_out_sum,file_out_diff,file_out_product;
    integer read_status,i;


    fixed_point_arthematic uut(.clk(clk),
    .operand_1(a),
    .operand_2(b),
    .sum(sum),
    .diff(diff),
    .product(product));

    always #5 clk = ~clk;

    initial 
    begin
        clk=0;

        f1 = $fopen("operand_1_in_Q_2_14.txt","r");
        f2 = $fopen("operand_2_in_Q_4_12.txt","r");
        file_out_sum = $fopen("sum_verilog_out.txt","w");
        file_out_diff = $fopen("diff_verilog_out.txt","w");
        file_out_product = $fopen("product_verilog_out.txt","w");

        $dumpfile("wave.vcd");
        $dumpvars(0, fixed_point_arthematic_tb);
        // $monitor($time,"a=%d b=%d,sum = %d",a,b,sum);
        

        // while (!($feof(f1) || $feof(f2)))
        for(i=0;i<=240;i++)
        begin
             #10
            read_status = $fscanf(f1, "%d\n",a);
            read_status = $fscanf(f2, "%d\n",b);

            if ((sum != "X") && (diff != "X") && (product != "X")) 
            begin
            $fwrite(file_out_sum, "%d\n", sum);
            $fwrite(file_out_diff, "%d\n", diff);
            $fwrite(file_out_product, "%d\n", product);
            end
        end
        $fclose(f1);
        $fclose(f2);
        $fclose(file_out_sum);
        $fclose(file_out_diff);
        $fclose(file_out_product);

        $finish;

    end

endmodule

FPGA/Experiment_2/wave.vcd
$date
	Mon Feb 17 01:14:35 2025
$end
$version
	Icarus Verilog
$end
$timescale
	1ps
$end
$scope module fixed_point_arthematic_tb $end
$var wire 18 ! sum [17:0] $end
$var wire 35 " product [34:0] $end
$var wire 18 # diff [17:0] $end
$var reg 17 $ a [16:0] $end
$var reg 17 % b [16:0] $end
$var reg 1 & clk $end
$var integer 32 ' f1 [31:0] $end
$var integer 32 ( f2 [31:0] $end
$var integer 32 ) file_out_diff [31:0] $end
$var integer 32 * file_out_product [31:0] $end
$var integer 32 + file_out_sum [31:0] $end
$var integer 32 , i [31:0] $end
$var integer 32 - read_status [31:0] $end
$scope module uut $end
$var wire 1 & clk $end
$var wire 17 . operand_1 [16:0] $end
$var wire 17 / operand_2 [16:0] $end
$var reg 18 0 diff [17:0] $end
$var reg 35 1 product [34:0] $end
$var reg 18 2 sum [17:0] $end
$upscope $end
$upscope $end
$enddefinitions $end
#0
$dumpvars
bx 2
bx 1
bx 0
bx /
bx .
bx -
b0 ,
b10000000000000000000000000000101 +
b10000000000000000000000000000111 *
b10000000000000000000000000000110 )
b10000000000000000000000000000100 (
b10000000000000000000000000000011 '
0&
bx %
bx $
bx #
bx "
bx !
$end
#50000
b0xxxxxxxxxxxxxxxxxxxxx "
b0xxxxxxxxxxxxxxxxxxxxx 1
1&
#100000
0&
b1 ,
b0 %
b0 /
b1 -
b0 $
b0 .
#150000
b0 "
b0 1
b0 #
b0 0
b0 !
b0 2
1&
#200000
0&
b10 ,
b10000101101 %
b10000101101 /
b1000010110101 $
b1000010110101 .
#250000
b10001011100 "
b10001011100 1
b1 #
b1 0
b10000101101001 !
b10000101101001 2
1&
#300000
0&
b11 ,
b100001001000 %
b100001001000 /
b10000100100001 $
b10000100100001 .
#350000
b1000100100101 "
b1000100100101 1
b100001001000001 !
b100001001000001 2
1&
#400000
0&
b100 ,
b110000111111 %
b110000111111 /
b11000011111100 $
b11000011111100 .
#450000
b10010101111101 "
b10010101111101 1
b0 #
b0 0
b110000111111000 !
b110000111111000 2
1&
#500000
0&
b101 ,
b1000000000000 %
b1000000000000 /
b100000000000000 $
b100000000000000 .
#550000
b100000000000000 "
b100000000000000 1
b1000000000000000 !
b1000000000000000 2
1&
#600000
0&
b110 ,
b1001101111011 %
b1001101111011 /
b100110111101100 $
b100110111101100 .
#650000
b101111011011111 "
b101111011011111 1
b1001101111011000 !
b1001101111011000 2
1&
#700000
0&
b111 ,
b1011010100001 %
b1011010100001 /
b101101010000010 $
b101101010000010 .
#750000
b1000000000000001 "
b1000000000000001 1
b111111111111111110 #
b111111111111111110 0
b1011010100000110 !
b1011010100000110 2
1&
#800000
0&
b1000 ,
b1100101100011 %
b1100101100011 /
b110010110001101 $
b110010110001101 .
#850000
b1010000100100000 "
b1010000100100000 1
b1 #
b1 0
b1100101100011001 !
b1100101100011001 2
1&
#900000
0&
b1001 ,
b1101110110110 %
b1101110110110 /
b110111011011010 $
b110111011011010 .
#950000
b1011111111111100 "
b1011111111111100 1
b10 #
b10 0
b1101110110110010 !
b1101110110110010 2
1&
#1000000
0&
b1010 ,
b1110110010000 %
b1110110010000 /
b111011001000010 $
b111011001000010 .
#1050000
b1101101001111111 "
b1101101001111111 1
b1110110010000010 !
b1110110010000010 2
1&
#1100000
0&
b1011 ,
b1111011101001 %
b1111011101001 /
b111101110100011 $
b111101110100011 .
#1150000
b1110111011011010 "
b1110111011011010 1
b111111111111111111 #
b111111111111111111 0
b1111011101000111 !
b1111011101000111 2
1&
#1200000
0&
b1100 ,
b1111110111010 %
b1111110111010 /
b111111011101000 $
b111111011101000 .
#1250000
b1111101110100100 "
b1111101110100100 1
b0 #
b0 0
b1111110111010000 !
b1111110111010000 2
1&
#1300000
0&
b1101 ,
b10000000000000 %
b10000000000000 /
b1000000000000000 $
b1000000000000000 .
#1350000
b10000000000000000 "
b10000000000000000 1
b10000000000000000 !
b10000000000000000 2
1&
#1400000
0&
b1110 ,
b1111110111010 %
b1111110111010 /
b111111011101000 $
b111111011101000 .
#1450000
b1111101110100100 "
b1111101110100100 1
b1111110111010000 !
b1111110111010000 2
1&
#1500000
0&
b1111 ,
b1111011101001 %
b1111011101001 /
b111101110100011 $
b111101110100011 .
#1550000
b1110111011011010 "
b1110111011011010 1
b111111111111111111 #
b111111111111111111 0
b1111011101000111 !
b1111011101000111 2
1&
#1600000
0&
b10000 ,
b1110110010000 %
b1110110010000 /
b111011001000010 $
b111011001000010 .
#1650000
b1101101001111111 "
b1101101001111111 1
b10 #
b10 0
b1110110010000010 !
b1110110010000010 2
1&
#1700000
0&
b10001 ,
b1101110110110 %
b1101110110110 /
b110111011011010 $
b110111011011010 .
#1750000
b1011111111111100 "
b1011111111111100 1
b1101110110110010 !
b1101110110110010 2
1&
#1800000
0&
b10010 ,
b1100101100011 %
b1100101100011 /
b110010110001101 $
b110010110001101 .
#1850000
b1010000100100000 "
b1010000100100000 1
b1 #
b1 0
b1100101100011001 !
b1100101100011001 2
1&
#1900000
0&
b10011 ,
b1011010100001 %
b1011010100001 /
b101101010000010 $
b101101010000010 .
#1950000
b1000000000000001 "
b1000000000000001 1
b111111111111111110 #
b111111111111111110 0
b1011010100000110 !
b1011010100000110 2
1&
#2000000
0&
b10100 ,
b1001101111011 %
b1001101111011 /
b100110111101100 $
b100110111101100 .
#2050000
b101111011011111 "
b101111011011111 1
b0 #
b0 0
b1001101111011000 !
b1001101111011000 2
1&
#2100000
0&
b10101 ,
b1000000000000 %
b1000000000000 /
b100000000000000 $
b100000000000000 .
#2150000
b100000000000000 "
b100000000000000 1
b1000000000000000 !
b1000000000000000 2
1&
#2200000
0&
b10110 ,
b110000111111 %
b110000111111 /
b11000011111100 $
b11000011111100 .
#2250000
b10010101111101 "
b10010101111101 1
b110000111111000 !
b110000111111000 2
1&
#2300000
0&
b10111 ,
b100001001000 %
b100001001000 /
b10000100100001 $
b10000100100001 .
#2350000
b1000100100101 "
b1000100100101 1
b1 #
b1 0
b100001001000001 !
b100001001000001 2
1&
#2400000
0&
b11000 ,
b10000101101 %
b10000101101 /
b1000010110101 $
b1000010110101 .
#2450000
b10001011100 "
b10001011100 1
b10000101101001 !
b10000101101001 2
1&
#2500000
0&
b11001 ,
b0 %
b0 /
b0 $
b0 .
#2550000
b0 "
b0 1
b0 #
b0 0
b0 !
b0 2
1&
#2600000
0&
b11010 ,
b11111101111010011 %
b11111101111010011 /
b11110111101001011 $
b11110111101001011 .
#2650000
b10001011100 "
b10001011100 1
b111111111111111111 #
b111111111111111111 0
b111101111010010111 !
b111101111010010111 2
1&
#2700000
0&
b11011 ,
b11111011110111000 %
b11111011110111000 /
b11101111011011111 $
b11101111011011111 .
#2750000
b1000100100101 "
b1000100100101 1
b111011110110111111 !
b111011110110111111 2
1&
#2800000
0&
b11100 ,
b11111001111000001 %
b11111001111000001 /
b11100111100000100 $
b11100111100000100 .
#2850000
b10010101111101 "
b10010101111101 1
b0 #
b0 0
b111001111000001000 !
b111001111000001000 2
1&
#2900000
0&
b11101 ,
b11111000000000000 %
b11111000000000000 /
b11100000000000000 $
b11100000000000000 .
#2950000
b100000000000000 "
b100000000000000 1
b111000000000000000 !
b111000000000000000 2
1&
#3000000
0&
b11110 ,
b11110110010000101 %
b11110110010000101 /
b11011001000010100 $
b11011001000010100 .
#3050000
b101111011011111 "
b101111011011111 1
b110110010000101000 !
b110110010000101000 2
1&
#3100000
0&
b11111 ,
b11110100101011111 %
b11110100101011111 /
b11010010101111110 $
b11010010101111110 .
#3150000
b1000000000000001 "
b1000000000000001 1
b10 #
b10 0
b110100101011111010 !
b110100101011111010 2
1&
#3200000
0&
b100000 ,
b11110011010011101 %
b11110011010011101 /
b11001101001110011 $
b11001101001110011 .
#3250000
b1010000100100000 "
b1010000100100000 1
b111111111111111111 #
b111111111111111111 0
b110011010011100111 !
b110011010011100111 2
1&
#3300000
0&
b100001 ,
b11110010001001010 %
b11110010001001010 /
b11001000100100110 $
b11001000100100110 .
#3350000
b1011111111111100 "
b1011111111111100 1
b111111111111111110 #
b111111111111111110 0
b110010001001001110 !
b110010001001001110 2
1&
#3400000
0&
b100010 ,
b11110001001110000 %
b11110001001110000 /
b11000100110111110 $
b11000100110111110 .
#3450000
b1101101001111111 "
b1101101001111111 1
b110001001101111110 !
b110001001101111110 2
1&
#3500000
0&
b100011 ,
b11110000100010111 %
b11110000100010111 /
b11000010001011101 $
b11000010001011101 .
#3550000
b1110111011011010 "
b1110111011011010 1
b1 #
b1 0
b110000100010111001 !
b110000100010111001 2
1&
#3600000
0&
b100100 ,
b11110000001000110 %
b11110000001000110 /
b11000000100011000 $
b11000000100011000 .
#3650000
b1111101110100100 "
b1111101110100100 1
b0 #
b0 0
b110000001000110000 !
b110000001000110000 2
1&
#3700000
0&
b100101 ,
b11110000000000000 %
b11110000000000000 /
b11000000000000000 $
b11000000000000000 .
#3750000
b10000000000000000 "
b10000000000000000 1
b110000000000000000 !
b110000000000000000 2
1&
#3800000
0&
b100110 ,
b11110000001000110 %
b11110000001000110 /
b11000000100011000 $
b11000000100011000 .
#3850000
b1111101110100100 "
b1111101110100100 1
b110000001000110000 !
b110000001000110000 2
1&
#3900000
0&
b100111 ,
b11110000100010111 %
b11110000100010111 /
b11000010001011101 $
b11000010001011101 .
#3950000
b1110111011011010 "
b1110111011011010 1
b1 #
b1 0
b110000100010111001 !
b110000100010111001 2
1&
#4000000
0&
b101000 ,
b11110001001110000 %
b11110001001110000 /
b11000100110111110 $
b11000100110111110 .
#4050000
b1101101001111111 "
b1101101001111111 1
b111111111111111110 #
b111111111111111110 0
b110001001101111110 !
b110001001101111110 2
1&
#4100000
0&
b101001 ,
b11110010001001010 %
b11110010001001010 /
b11001000100100110 $
b11001000100100110 .
#4150000
b1011111111111100 "
b1011111111111100 1
b110010001001001110 !
b110010001001001110 2
1&
#4200000
0&
b101010 ,
b11110011010011101 %
b11110011010011101 /
b11001101001110011 $
b11001101001110011 .
#4250000
b1010000100100000 "
b1010000100100000 1
b111111111111111111 #
b111111111111111111 0
b110011010011100111 !
b110011010011100111 2
1&
#4300000
0&
b101011 ,
b11110100101011111 %
b11110100101011111 /
b11010010101111110 $
b11010010101111110 .
#4350000
b1000000000000001 "
b1000000000000001 1
b10 #
b10 0
b110100101011111010 !
b110100101011111010 2
1&
#4400000
0&
b101100 ,
b11110110010000101 %
b11110110010000101 /
b11011001000010100 $
b11011001000010100 .
#4450000
b101111011011111 "
b101111011011111 1
b0 #
b0 0
b110110010000101000 !
b110110010000101000 2
1&
#4500000
0&
b101101 ,
b11111000000000000 %
b11111000000000000 /
b11100000000000000 $
b11100000000000000 .
#4550000
b100000000000000 "
b100000000000000 1
b111000000000000000 !
b111000000000000000 2
1&
#4600000
0&
b101110 ,
b11111001111000001 %
b11111001111000001 /
b11100111100000100 $
b11100111100000100 .
#4650000
b10010101111101 "
b10010101111101 1
b111001111000001000 !
b111001111000001000 2
1&
#4700000
0&
b101111 ,
b11111011110111000 %
b11111011110111000 /
b11101111011011111 $
b11101111011011111 .
#4750000
b1000100100101 "
b1000100100101 1
b111111111111111111 #
b111111111111111111 0
b111011110110111111 !
b111011110110111111 2
1&
#4800000
0&
b110000 ,
b11111101111010011 %
b11111101111010011 /
b11110111101001011 $
b11110111101001011 .
#4850000
b10001011100 "
b10001011100 1
b111101111010010111 !
b111101111010010111 2
1&
#4900000
0&
b110001 ,
b0 %
b0 /
b0 $
b0 .
#4950000
b0 "
b0 1
b0 #
b0 0
b0 !
b0 2
1&
#5000000
0&
b110010 ,
b10000101101 %
b10000101101 /
b1000010110101 $
b1000010110101 .
#5050000
b10001011100 "
b10001011100 1
b1 #
b1 0
b10000101101001 !
b10000101101001 2
1&
#5100000
0&
b110011 ,
b100001001000 %
b100001001000 /
b10000100100001 $
b10000100100001 .
#5150000
b1000100100101 "
b1000100100101 1
b100001001000001 !
b100001001000001 2
1&
#5200000
0&
b110100 ,
b110000111111 %
b110000111111 /
b11000011111100 $
b11000011111100 .
#5250000
b10010101111101 "
b10010101111101 1
b0 #
b0 0
b110000111111000 !
b110000111111000 2
1&
#5300000
0&
b110101 ,
b1000000000000 %
b1000000000000 /
b100000000000000 $
b100000000000000 .
#5350000
b100000000000000 "
b100000000000000 1
b1000000000000000 !
b1000000000000000 2
1&
#5400000
0&
b110110 ,
b1001101111011 %
b1001101111011 /
b100110111101100 $
b100110111101100 .
#5450000
b101111011011111 "
b101111011011111 1
b1001101111011000 !
b1001101111011000 2
1&
#5500000
0&
b110111 ,
b1011010100001 %
b1011010100001 /
b101101010000010 $
b101101010000010 .
#5550000
b1000000000000001 "
b1000000000000001 1
b111111111111111110 #
b111111111111111110 0
b1011010100000110 !
b1011010100000110 2
1&
#5600000
0&
b111000 ,
b1100101100011 %
b1100101100011 /
b110010110001101 $
b110010110001101 .
#5650000
b1010000100100000 "
b1010000100100000 1
b1 #
b1 0
b1100101100011001 !
b1100101100011001 2
1&
#5700000
0&
b111001 ,
b1101110110110 %
b1101110110110 /
b110111011011010 $
b110111011011010 .
#5750000
b1011111111111100 "
b1011111111111100 1
b10 #
b10 0
b1101110110110010 !
b1101110110110010 2
1&
#5800000
0&
b111010 ,
b1110110010000 %
b1110110010000 /
b111011001000010 $
b111011001000010 .
#5850000
b1101101001111111 "
b1101101001111111 1
b1110110010000010 !
b1110110010000010 2
1&
#5900000
0&
b111011 ,
b1111011101001 %
b1111011101001 /
b111101110100011 $
b111101110100011 .
#5950000
b1110111011011010 "
b1110111011011010 1
b111111111111111111 #
b111111111111111111 0
b1111011101000111 !
b1111011101000111 2
1&
#6000000
0&
b111100 ,
b1111110111010 %
b1111110111010 /
b111111011101000 $
b111111011101000 .
#6050000
b1111101110100100 "
b1111101110100100 1
b0 #
b0 0
b1111110111010000 !
b1111110111010000 2
1&
#6100000
0&
b111101 ,
b10000000000000 %
b10000000000000 /
b1000000000000000 $
b1000000000000000 .
#6150000
b10000000000000000 "
b10000000000000000 1
b10000000000000000 !
b10000000000000000 2
1&
#6200000
0&
b111110 ,
b1111110111010 %
b1111110111010 /
b111111011101000 $
b111111011101000 .
#6250000
b1111101110100100 "
b1111101110100100 1
b1111110111010000 !
b1111110111010000 2
1&
#6300000
0&
b111111 ,
b1111011101001 %
b1111011101001 /
b111101110100011 $
b111101110100011 .
#6350000
b1110111011011010 "
b1110111011011010 1
b111111111111111111 #
b111111111111111111 0
b1111011101000111 !
b1111011101000111 2
1&
#6400000
0&
b1000000 ,
b1110110010000 %
b1110110010000 /
b111011001000010 $
b111011001000010 .
#6450000
b1101101001111111 "
b1101101001111111 1
b10 #
b10 0
b1110110010000010 !
b1110110010000010 2
1&
#6500000
0&
b1000001 ,
b1101110110110 %
b1101110110110 /
b110111011011010 $
b110111011011010 .
#6550000
b1011111111111100 "
b1011111111111100 1
b1101110110110010 !
b1101110110110010 2
1&
#6600000
0&
b1000010 ,
b1100101100011 %
b1100101100011 /
b110010110001101 $
b110010110001101 .
#6650000
b1010000100100000 "
b1010000100100000 1
b1 #
b1 0
b1100101100011001 !
b1100101100011001 2
1&
#6700000
0&
b1000011 ,
b1011010100001 %
b1011010100001 /
b101101010000010 $
b101101010000010 .
#6750000
b1000000000000001 "
b1000000000000001 1
b111111111111111110 #
b111111111111111110 0
b1011010100000110 !
b1011010100000110 2
1&
#6800000
0&
b1000100 ,
b1001101111011 %
b1001101111011 /
b100110111101100 $
b100110111101100 .
#6850000
b101111011011111 "
b101111011011111 1
b0 #
b0 0
b1001101111011000 !
b1001101111011000 2
1&
#6900000
0&
b1000101 ,
b1000000000000 %
b1000000000000 /
b100000000000000 $
b100000000000000 .
#6950000
b100000000000000 "
b100000000000000 1
b1000000000000000 !
b1000000000000000 2
1&
#7000000
0&
b1000110 ,
b110000111111 %
b110000111111 /
b11000011111100 $
b11000011111100 .
#7050000
b10010101111101 "
b10010101111101 1
b110000111111000 !
b110000111111000 2
1&
#7100000
0&
b1000111 ,
b100001001000 %
b100001001000 /
b10000100100001 $
b10000100100001 .
#7150000
b1000100100101 "
b1000100100101 1
b1 #
b1 0
b100001001000001 !
b100001001000001 2
1&
#7200000
0&
b1001000 ,
b10000101101 %
b10000101101 /
b1000010110101 $
b1000010110101 .
#7250000
b10001011100 "
b10001011100 1
b10000101101001 !
b10000101101001 2
1&
#7300000
0&
b1001001 ,
b0 %
b0 /
b0 $
b0 .
#7350000
b0 "
b0 1
b0 #
b0 0
b0 !
b0 2
1&
#7400000
0&
b1001010 ,
b11111101111010011 %
b11111101111010011 /
b11110111101001011 $
b11110111101001011 .
#7450000
b10001011100 "
b10001011100 1
b111111111111111111 #
b111111111111111111 0
b111101111010010111 !
b111101111010010111 2
1&
#7500000
0&
b1001011 ,
b11111011110111000 %
b11111011110111000 /
b11101111011011111 $
b11101111011011111 .
#7550000
b1000100100101 "
b1000100100101 1
b111011110110111111 !
b111011110110111111 2
1&
#7600000
0&
b1001100 ,
b11111001111000001 %
b11111001111000001 /
b11100111100000100 $
b11100111100000100 .
#7650000
b10010101111101 "
b10010101111101 1
b0 #
b0 0
b111001111000001000 !
b111001111000001000 2
1&
#7700000
0&
b1001101 ,
b11111000000000000 %
b11111000000000000 /
b11100000000000000 $
b11100000000000000 .
#7750000
b100000000000000 "
b100000000000000 1
b111000000000000000 !
b111000000000000000 2
1&
#7800000
0&
b1001110 ,
b11110110010000101 %
b11110110010000101 /
b11011001000010100 $
b11011001000010100 .
#7850000
b101111011011111 "
b101111011011111 1
b110110010000101000 !
b110110010000101000 2
1&
#7900000
0&
b1001111 ,
b11110100101011111 %
b11110100101011111 /
b11010010101111110 $
b11010010101111110 .
#7950000
b1000000000000001 "
b1000000000000001 1
b10 #
b10 0
b110100101011111010 !
b110100101011111010 2
1&
#8000000
0&
b1010000 ,
b11110011010011101 %
b11110011010011101 /
b11001101001110011 $
b11001101001110011 .
#8050000
b1010000100100000 "
b1010000100100000 1
b111111111111111111 #
b111111111111111111 0
b110011010011100111 !
b110011010011100111 2
1&
#8100000
0&
b1010001 ,
b11110010001001010 %
b11110010001001010 /
b11001000100100110 $
b11001000100100110 .
#8150000
b1011111111111100 "
b1011111111111100 1
b111111111111111110 #
b111111111111111110 0
b110010001001001110 !
b110010001001001110 2
1&
#8200000
0&
b1010010 ,
b11110001001110000 %
b11110001001110000 /
b11000100110111110 $
b11000100110111110 .
#8250000
b1101101001111111 "
b1101101001111111 1
b110001001101111110 !
b110001001101111110 2
1&
#8300000
0&
b1010011 ,
b11110000100010111 %
b11110000100010111 /
b11000010001011101 $
b11000010001011101 .
#8350000
b1110111011011010 "
b1110111011011010 1
b1 #
b1 0
b110000100010111001 !
b110000100010111001 2
1&
#8400000
0&
b1010100 ,
b11110000001000110 %
b11110000001000110 /
b11000000100011000 $
b11000000100011000 .
#8450000
b1111101110100100 "
b1111101110100100 1
b0 #
b0 0
b110000001000110000 !
b110000001000110000 2
1&
#8500000
0&
b1010101 ,
b11110000000000000 %
b11110000000000000 /
b11000000000000000 $
b11000000000000000 .
#8550000
b10000000000000000 "
b10000000000000000 1
b110000000000000000 !
b110000000000000000 2
1&
#8600000
0&
b1010110 ,
b11110000001000110 %
b11110000001000110 /
b11000000100011000 $
b11000000100011000 .
#8650000
b1111101110100100 "
b1111101110100100 1
b110000001000110000 !
b110000001000110000 2
1&
#8700000
0&
b1010111 ,
b11110000100010111 %
b11110000100010111 /
b11000010001011101 $
b11000010001011101 .
#8750000
b1110111011011010 "
b1110111011011010 1
b1 #
b1 0
b110000100010111001 !
b110000100010111001 2
1&
#8800000
0&
b1011000 ,
b11110001001110000 %
b11110001001110000 /
b11000100110111110 $
b11000100110111110 .
#8850000
b1101101001111111 "
b1101101001111111 1
b111111111111111110 #
b111111111111111110 0
b110001001101111110 !
b110001001101111110 2
1&
#8900000
0&
b1011001 ,
b11110010001001010 %
b11110010001001010 /
b11001000100100110 $
b11001000100100110 .
#8950000
b1011111111111100 "
b1011111111111100 1
b110010001001001110 !
b110010001001001110 2
1&
#9000000
0&
b1011010 ,
b11110011010011101 %
b11110011010011101 /
b11001101001110011 $
b11001101001110011 .
#9050000
b1010000100100000 "
b1010000100100000 1
b111111111111111111 #
b111111111111111111 0
b110011010011100111 !
b110011010011100111 2
1&
#9100000
0&
b1011011 ,
b11110100101011111 %
b11110100101011111 /
b11010010101111110 $
b11010010101111110 .
#9150000
b1000000000000001 "
b1000000000000001 1
b10 #
b10 0
b110100101011111010 !
b110100101011111010 2
1&
#9200000
0&
b1011100 ,
b11110110010000101 %
b11110110010000101 /
b11011001000010100 $
b11011001000010100 .
#9250000
b101111011011111 "
b101111011011111 1
b0 #
b0 0
b110110010000101000 !
b110110010000101000 2
1&
#9300000
0&
b1011101 ,
b11111000000000000 %
b11111000000000000 /
b11100000000000000 $
b11100000000000000 .
#9350000
b100000000000000 "
b100000000000000 1
b111000000000000000 !
b111000000000000000 2
1&
#9400000
0&
b1011110 ,
b11111001111000001 %
b11111001111000001 /
b11100111100000100 $
b11100111100000100 .
#9450000
b10010101111101 "
b10010101111101 1
b111001111000001000 !
b111001111000001000 2
1&
#9500000
0&
b1011111 ,
b11111011110111000 %
b11111011110111000 /
b11101111011011111 $
b11101111011011111 .
#9550000
b1000100100101 "
b1000100100101 1
b111111111111111111 #
b111111111111111111 0
b111011110110111111 !
b111011110110111111 2
1&
#9600000
0&
b1100000 ,
b11111101111010011 %
b11111101111010011 /
b11110111101001011 $
b11110111101001011 .
#9650000
b10001011100 "
b10001011100 1
b111101111010010111 !
b111101111010010111 2
1&
#9700000
0&
b1100001 ,
b0 %
b0 /
b0 $
b0 .
#9750000
b0 "
b0 1
b0 #
b0 0
b0 !
b0 2
1&
#9800000
0&
b1100010 ,
b10000101101 %
b10000101101 /
b1000010110101 $
b1000010110101 .
#9850000
b10001011100 "
b10001011100 1
b1 #
b1 0
b10000101101001 !
b10000101101001 2
1&
#9900000
0&
b1100011 ,
b100001001000 %
b100001001000 /
b10000100100001 $
b10000100100001 .
#9950000
b1000100100101 "
b1000100100101 1
b100001001000001 !
b100001001000001 2
1&
#10000000
0&
b1100100 ,
b110000111111 %
b110000111111 /
b11000011111100 $
b11000011111100 .
#10050000
b10010101111101 "
b10010101111101 1
b0 #
b0 0
b110000111111000 !
b110000111111000 2
1&
#10100000
0&
b1100101 ,
b1000000000000 %
b1000000000000 /
b100000000000000 $
b100000000000000 .
#10150000
b100000000000000 "
b100000000000000 1
b1000000000000000 !
b1000000000000000 2
1&
#10200000
0&
b1100110 ,
b1001101111011 %
b1001101111011 /
b100110111101100 $
b100110111101100 .
#10250000
b101111011011111 "
b101111011011111 1
b1001101111011000 !
b1001101111011000 2
1&
#10300000
0&
b1100111 ,
b1011010100001 %
b1011010100001 /
b101101010000010 $
b101101010000010 .
#10350000
b1000000000000001 "
b1000000000000001 1
b111111111111111110 #
b111111111111111110 0
b1011010100000110 !
b1011010100000110 2
1&
#10400000
0&
b1101000 ,
b1100101100011 %
b1100101100011 /
b110010110001101 $
b110010110001101 .
#10450000
b1010000100100000 "
b1010000100100000 1
b1 #
b1 0
b1100101100011001 !
b1100101100011001 2
1&
#10500000
0&
b1101001 ,
b1101110110110 %
b1101110110110 /
b110111011011010 $
b110111011011010 .
#10550000
b1011111111111100 "
b1011111111111100 1
b10 #
b10 0
b1101110110110010 !
b1101110110110010 2
1&
#10600000
0&
b1101010 ,
b1110110010000 %
b1110110010000 /
b111011001000010 $
b111011001000010 .
#10650000
b1101101001111111 "
b1101101001111111 1
b1110110010000010 !
b1110110010000010 2
1&
#10700000
0&
b1101011 ,
b1111011101001 %
b1111011101001 /
b111101110100011 $
b111101110100011 .
#10750000
b1110111011011010 "
b1110111011011010 1
b111111111111111111 #
b111111111111111111 0
b1111011101000111 !
b1111011101000111 2
1&
#10800000
0&
b1101100 ,
b1111110111010 %
b1111110111010 /
b111111011101000 $
b111111011101000 .
#10850000
b1111101110100100 "
b1111101110100100 1
b0 #
b0 0
b1111110111010000 !
b1111110111010000 2
1&
#10900000
0&
b1101101 ,
b10000000000000 %
b10000000000000 /
b1000000000000000 $
b1000000000000000 .
#10950000
b10000000000000000 "
b10000000000000000 1
b10000000000000000 !
b10000000000000000 2
1&
#11000000
0&
b1101110 ,
b1111110111010 %
b1111110111010 /
b111111011101000 $
b111111011101000 .
#11050000
b1111101110100100 "
b1111101110100100 1
b1111110111010000 !
b1111110111010000 2
1&
#11100000
0&
b1101111 ,
b1111011101001 %
b1111011101001 /
b111101110100011 $
b111101110100011 .
#11150000
b1110111011011010 "
b1110111011011010 1
b111111111111111111 #
b111111111111111111 0
b1111011101000111 !
b1111011101000111 2
1&
#11200000
0&
b1110000 ,
b1110110010000 %
b1110110010000 /
b111011001000010 $
b111011001000010 .
#11250000
b1101101001111111 "
b1101101001111111 1
b10 #
b10 0
b1110110010000010 !
b1110110010000010 2
1&
#11300000
0&
b1110001 ,
b1101110110110 %
b1101110110110 /
b110111011011010 $
b110111011011010 .
#11350000
b1011111111111100 "
b1011111111111100 1
b1101110110110010 !
b1101110110110010 2
1&
#11400000
0&
b1110010 ,
b1100101100011 %
b1100101100011 /
b110010110001101 $
b110010110001101 .
#11450000
b1010000100100000 "
b1010000100100000 1
b1 #
b1 0
b1100101100011001 !
b1100101100011001 2
1&
#11500000
0&
b1110011 ,
b1011010100001 %
b1011010100001 /
b101101010000010 $
b101101010000010 .
#11550000
b1000000000000001 "
b1000000000000001 1
b111111111111111110 #
b111111111111111110 0
b1011010100000110 !
b1011010100000110 2
1&
#11600000
0&
b1110100 ,
b1001101111011 %
b1001101111011 /
b100110111101100 $
b100110111101100 .
#11650000
b101111011011111 "
b101111011011111 1
b0 #
b0 0
b1001101111011000 !
b1001101111011000 2
1&
#11700000
0&
b1110101 ,
b1000000000000 %
b1000000000000 /
b100000000000000 $
b100000000000000 .
#11750000
b100000000000000 "
b100000000000000 1
b1000000000000000 !
b1000000000000000 2
1&
#11800000
0&
b1110110 ,
b110000111111 %
b110000111111 /
b11000011111100 $
b11000011111100 .
#11850000
b10010101111101 "
b10010101111101 1
b110000111111000 !
b110000111111000 2
1&
#11900000
0&
b1110111 ,
b100001001000 %
b100001001000 /
b10000100100001 $
b10000100100001 .
#11950000
b1000100100101 "
b1000100100101 1
b1 #
b1 0
b100001001000001 !
b100001001000001 2
1&
#12000000
0&
b1111000 ,
b10000101101 %
b10000101101 /
b1000010110101 $
b1000010110101 .
#12050000
b10001011100 "
b10001011100 1
b10000101101001 !
b10000101101001 2
1&
#12100000
0&
b1111001 ,
b0 %
b0 /
b0 $
b0 .
#12150000
b0 "
b0 1
b0 #
b0 0
b0 !
b0 2
1&
#12200000
0&
b1111010 ,
b11111101111010011 %
b11111101111010011 /
b11110111101001011 $
b11110111101001011 .
#12250000
b10001011100 "
b10001011100 1
b111111111111111111 #
b111111111111111111 0
b111101111010010111 !
b111101111010010111 2
1&
#12300000
0&
b1111011 ,
b11111011110111000 %
b11111011110111000 /
b11101111011011111 $
b11101111011011111 .
#12350000
b1000100100101 "
b1000100100101 1
b111011110110111111 !
b111011110110111111 2
1&
#12400000
0&
b1111100 ,
b11111001111000001 %
b11111001111000001 /
b11100111100000100 $
b11100111100000100 .
#12450000
b10010101111101 "
b10010101111101 1
b0 #
b0 0
b111001111000001000 !
b111001111000001000 2
1&
#12500000
0&
b1111101 ,
b11111000000000000 %
b11111000000000000 /
b11100000000000000 $
b11100000000000000 .
