FPGA/mini_project/gps_l1_c_prn_code_generation.v
module prn_code_generator(
    input wire clk,
    input wire rst,
    input wire start,
    input wire [2:0] prn_id,
    input wire pd,
    output reg [13:0] addr,
    output reg out_valid,
    output reg prn_bit
);

parameter N = 10223;
reg [13:0] i;
reg [13:0] weil_index;
reg [13:0] insertion_index;
reg [13:0] insert_end;
reg [6:0] expansion_bits;

reg legendre_rom [0:N-1];

initial 
begin
    expansion_bits[0] = 0;
    expansion_bits[1] = 1;
    expansion_bits[2] = 1;
    expansion_bits[3] = 0;
    expansion_bits[4] = 1;
    expansion_bits[5] = 0;
    expansion_bits[6] = 0;

    $readmemb("legendre.mem", legendre_rom);
    
end


always @(*) 
begin
    case ({pd, prn_id})
        
        /* Data prn code settings */
        4'b1001: begin weil_index = 5097; insertion_index = 181; end
        4'b1010: begin weil_index = 5110; insertion_index = 359; end
        4'b1011: begin weil_index = 5079; insertion_index = 72;  end
        4'b1100: begin weil_index = 4403; insertion_index = 1110; end
        4'b1101: begin weil_index = 4121; insertion_index = 1480; end

        /* pilot prncodes settings */
        4'b0001: begin weil_index = 5111; insertion_index = 412; end
        4'b0010: begin weil_index = 5109; insertion_index = 161; end
        4'b0011: begin weil_index = 5108; insertion_index = 1;   end
        4'b0100: begin weil_index = 5106; insertion_index = 303; end
        4'b0101: begin weil_index = 5103; insertion_index = 207; end
        default: begin weil_index = 0; insertion_index = 0; end
    endcase
        insert_end = insertion_index + 7;
        //$display("pd = %d prn_id = %d\n",pd,prn_id);
        //$display("weil_index = %d insertion_index = %d insert_end = %d\n",weil_index,insertion_index,insert_end);

end


assign legendre_i        = legendre_rom[i];
assign legendre_shifted  = legendre_rom[(i + weil_index) % N];


always @(posedge clk or posedge rst) 
begin
    if (rst) 
    begin
        i <= 0;
        addr <= 0;
        out_valid <= 0;
    end 
    else if (start) 
    begin
        if (i < N) 
        begin
            if (i >= insertion_index && i < insert_end) 
            begin
                prn_bit <= expansion_bits[i - insertion_index];
            end 
            else 
            begin
                prn_bit <= legendre_i ^ legendre_shifted;
            end
            addr <= i;
            i <= i + 1;
            out_valid <= 1;
        end 
        else 
        begin
            out_valid <= 0;
        end
    end
end

endmodule

FPGA/mini_project/gps_l1_prn_gen_tb.v
`timescale 1ns / 1ps

module prn_code_generator_tb;

    reg clk;
    reg rst;
    reg start;
    reg [2:0] prn_id;
    reg pd;

    wire [13:0] addr;
    wire out_valid;
    wire prn_bit;

    prn_code_generator uut (
        .clk(clk),
        .rst(rst),
        .start(start),
        .prn_id(prn_id),
        .pd(pd),
        .addr(addr),
        .out_valid(out_valid),
        .prn_bit(prn_bit)
    );

    always #5 clk = ~clk;

    integer f,i;

    initial 
    begin

        $dumpfile("wave.vcd");
        $dumpvars(0, prn_code_generator_tb);
        clk = 0;
        rst = 1;
        start = 0;
        prn_id = 3'b101;  
        pd = 1'b0;  //pd = 1 for data and pd = 0 for pilot       

        f = $fopen("prn_code_output.txt", "w");
        if (!f) 
        begin
            $display("Error: Could not open file.");
            $finish;
        end


        #20;
        rst = 0;
        start = 1;
        i = 0;
        prn_id = 3'b101;  //prn id
        pd = 1'b0;        //pd = 1 for data and pd = 0 for pilot 
        $display("pd = %d prn_id = %d\n",pd,prn_id);

        while (i < 10230) 
        begin
            @(posedge clk);
            if (out_valid) 
            begin
                $fwrite(f, "%b ", prn_bit);
                // $display("%d\n",prn_bit);
            end
            i=i+1;
        end
        $finish;

        $fclose(f);
    end

endmodule

FPGA/mini_project/wave.vcd
$date
	Thu Apr 24 15:26:05 2025
$end
$version
	Icarus Verilog
$end
$timescale
	1ps
$end
$scope module prn_code_generator_tb $end
$var wire 1 ! prn_bit $end
$var wire 1 " out_valid $end
$var wire 14 # addr [13:0] $end
$var reg 1 $ clk $end
$var reg 1 % pd $end
$var reg 3 & prn_id [2:0] $end
$var reg 1 ' rst $end
$var reg 1 ( start $end
$var integer 32 ) f [31:0] $end
$var integer 32 * i [31:0] $end
$scope module uut $end
$var wire 1 $ clk $end
$var wire 1 + legendre_i $end
$var wire 1 , legendre_shifted $end
$var wire 1 % pd $end
$var wire 3 - prn_id [2:0] $end
$var wire 1 ' rst $end
$var wire 1 ( start $end
$var reg 14 . addr [13:0] $end
$var reg 7 / expansion_bits [6:0] $end
$var reg 14 0 i [13:0] $end
$var reg 14 1 insert_end [13:0] $end
$var reg 14 2 insertion_index [13:0] $end
$var reg 1 " out_valid $end
$var reg 1 ! prn_bit $end
$var reg 14 3 weil_index [13:0] $end
$upscope $end
$upscope $end
$enddefinitions $end
#0
$dumpvars
b1001111101111 3
b11001111 2
b11010110 1
b0 0
b10110 /
b0 .
b101 -
1,
0+
bx *
b10000000000000000000000000000011 )
0(
1'
b101 &
0%
0$
b0 #
0"
x!
$end
#5000
1$
#10000
0$
#15000
1$
#20000
0$
b0 *
1(
0'
#25000
1"
1+
b1 0
1!
b1 *
1$
#30000
0$
#35000
b10 0
b1 #
b1 .
0!
b10 *
1$
#40000
0$
#45000
b11 0
b10 #
b10 .
b11 *
1$
#50000
0$
#55000
0,
b100 0
b11 #
b11 .
b100 *
1$
#60000
0$
#65000
0+
b101 0
b100 #
b100 .
1!
b101 *
1$
#70000
0$
#75000
1+
1,
b110 0
b101 #
b101 .
0!
b110 *
1$
#80000
0$
#85000
0,
b111 0
b110 #
b110 .
b111 *
1$
#90000
0$
#95000
b1000 0
b111 #
b111 .
1!
b1000 *
1$
#100000
0$
#105000
1,
b1001 0
b1000 #
b1000 .
b1001 *
1$
#110000
0$
#115000
0+
b1010 0
b1001 #
b1001 .
0!
b1010 *
1$
#120000
0$
#125000
0,
b1011 0
b1010 #
b1010 .
1!
b1011 *
1$
#130000
0$
#135000
1+
1,
b1100 0
b1011 #
b1011 .
0!
b1100 *
1$
#140000
0$
#145000
0+
b1101 0
b1100 #
b1100 .
b1101 *
1$
#150000
0$
#155000
1+
0,
b1110 0
b1101 #
b1101 .
1!
b1110 *
1$
#160000
0$
#165000
0+
b1111 0
b1110 #
b1110 .
b1111 *
1$
#170000
0$
#175000
1+
b10000 0
b1111 #
b1111 .
0!
b10000 *
1$
#180000
0$
#185000
0+
b10001 0
b10000 #
b10000 .
1!
b10001 *
1$
#190000
0$
#195000
1+
b10010 0
b10001 #
b10001 .
0!
b10010 *
1$
#200000
0$
#205000
0+
1,
b10011 0
b10010 #
b10010 .
1!
b10011 *
1$
#210000
0$
#215000
b10100 0
b10011 #
b10011 .
b10100 *
1$
#220000
0$
#225000
1+
b10101 0
b10100 #
b10100 .
b10101 *
1$
#230000
0$
#235000
0+
b10110 0
b10101 #
b10101 .
0!
b10110 *
1$
#240000
0$
#245000
1+
0,
b10111 0
b10110 #
b10110 .
1!
b10111 *
1$
#250000
0$
#255000
1,
b11000 0
b10111 #
b10111 .
b11000 *
1$
#260000
0$
#265000
0,
b11001 0
b11000 #
b11000 .
0!
b11001 *
1$
#270000
0$
#275000
0+
b11010 0
b11001 #
b11001 .
1!
b11010 *
1$
#280000
0$
#285000
1+
1,
b11011 0
b11010 #
b11010 .
0!
b11011 *
1$
#290000
0$
#295000
0,
b11100 0
b11011 #
b11011 .
b11100 *
1$
#300000
0$
#305000
0+
b11101 0
b11100 #
b11100 .
1!
b11101 *
1$
#310000
0$
#315000
1,
b11110 0
b11101 #
b11101 .
0!
b11110 *
1$
#320000
0$
#325000
1+
0,
b11111 0
b11110 #
b11110 .
1!
b11111 *
1$
#330000
0$
#335000
b100000 0
b11111 #
b11111 .
b100000 *
1$
#340000
0$
#345000
0+
1,
b100001 0
b100000 #
b100000 .
b100001 *
1$
#350000
0$
#355000
0,
b100010 0
b100001 #
b100001 .
b100010 *
1$
#360000
0$
#365000
1,
b100011 0
b100010 #
b100010 .
0!
b100011 *
1$
#370000
0$
#375000
1+
b100100 0
b100011 #
b100011 .
1!
b100100 *
1$
#380000
0$
#385000
0,
b100101 0
b100100 #
b100100 .
0!
b100101 *
1$
#390000
0$
#395000
0+
b100110 0
b100101 #
b100101 .
1!
b100110 *
1$
#400000
0$
#405000
1,
b100111 0
b100110 #
b100110 .
0!
b100111 *
1$
#410000
0$
#415000
b101000 0
b100111 #
b100111 .
1!
b101000 *
1$
#420000
0$
#425000
b101001 0
b101000 #
b101000 .
b101001 *
1$
#430000
0$
#435000
1+
0,
b101010 0
b101001 #
b101001 .
b101010 *
1$
#440000
0$
#445000
1,
b101011 0
b101010 #
b101010 .
b101011 *
1$
#450000
0$
#455000
0+
b101100 0
b101011 #
b101011 .
0!
b101100 *
1$
#460000
0$
#465000
b101101 0
b101100 #
b101100 .
1!
b101101 *
1$
#470000
0$
#475000
1+
b101110 0
b101101 #
b101101 .
b101110 *
1$
#480000
0$
#485000
0+
0,
b101111 0
b101110 #
b101110 .
0!
b101111 *
1$
#490000
0$
#495000
1+
b110000 0
b101111 #
b101111 .
b110000 *
1$
#500000
0$
#505000
1,
b110001 0
b110000 #
b110000 .
1!
b110001 *
1$
#510000
0$
#515000
b110010 0
b110001 #
b110001 .
0!
b110010 *
1$
#520000
0$
#525000
0+
b110011 0
b110010 #
b110010 .
b110011 *
1$
#530000
0$
#535000
0,
b110100 0
b110011 #
b110011 .
1!
b110100 *
1$
#540000
0$
#545000
1+
b110101 0
b110100 #
b110100 .
0!
b110101 *
1$
#550000
0$
#555000
b110110 0
b110101 #
b110101 .
1!
b110110 *
1$
#560000
0$
#565000
1,
b110111 0
b110110 #
b110110 .
b110111 *
1$
#570000
0$
#575000
b111000 0
b110111 #
b110111 .
0!
b111000 *
1$
#580000
0$
#585000
0+
0,
b111001 0
b111000 #
b111000 .
b111001 *
1$
#590000
0$
#595000
b111010 0
b111001 #
b111001 .
b111010 *
1$
#600000
0$
#605000
1,
b111011 0
b111010 #
b111010 .
b111011 *
1$
#610000
0$
#615000
0,
b111100 0
b111011 #
b111011 .
1!
b111100 *
1$
#620000
0$
#625000
1+
b111101 0
b111100 #
b111100 .
0!
b111101 *
1$
#630000
0$
#635000
1,
b111110 0
b111101 #
b111101 .
1!
b111110 *
1$
#640000
0$
#645000
0,
b111111 0
b111110 #
b111110 .
0!
b111111 *
1$
#650000
0$
#655000
1,
b1000000 0
b111111 #
b111111 .
1!
b1000000 *
1$
#660000
0$
#665000
b1000001 0
b1000000 #
b1000000 .
0!
b1000001 *
1$
#670000
0$
#675000
0+
0,
b1000010 0
b1000001 #
b1000001 .
b1000010 *
1$
#680000
0$
#685000
b1000011 0
b1000010 #
b1000010 .
b1000011 *
1$
#690000
0$
#695000
b1000100 0
b1000011 #
b1000011 .
b1000100 *
1$
#700000
0$
#705000
1+
1,
b1000101 0
b1000100 #
b1000100 .
b1000101 *
1$
#710000
0$
#715000
0+
0,
b1000110 0
b1000101 #
b1000101 .
b1000110 *
1$
#720000
0$
#725000
1+
b1000111 0
b1000110 #
b1000110 .
b1000111 *
1$
#730000
0$
#735000
1,
b1001000 0
b1000111 #
b1000111 .
1!
b1001000 *
1$
#740000
0$
#745000
b1001001 0
b1001000 #
b1001000 .
0!
b1001001 *
1$
#750000
0$
#755000
0,
b1001010 0
b1001001 #
b1001001 .
b1001010 *
1$
#760000
0$
#765000
b1001011 0
b1001010 #
b1001010 .
1!
b1001011 *
1$
#770000
0$
#775000
0+
b1001100 0
b1001011 #
b1001011 .
b1001100 *
1$
#780000
0$
#785000
b1001101 0
b1001100 #
b1001100 .
0!
b1001101 *
1$
#790000
0$
#795000
1,
b1001110 0
b1001101 #
b1001101 .
b1001110 *
1$
#800000
0$
#805000
0,
b1001111 0
b1001110 #
b1001110 .
1!
b1001111 *
1$
#810000
0$
#815000
1,
b1010000 0
b1001111 #
b1001111 .
0!
b1010000 *
1$
#820000
0$
#825000
1+
b1010001 0
b1010000 #
b1010000 .
1!
b1010001 *
1$
#830000
0$
#835000
0+
b1010010 0
b1010001 #
b1010001 .
0!
b1010010 *
1$
#840000
0$
#845000
1+
0,
b1010011 0
b1010010 #
b1010010 .
1!
b1010011 *
1$
#850000
0$
#855000
1,
b1010100 0
b1010011 #
b1010011 .
b1010100 *
1$
#860000
0$
#865000
0,
b1010101 0
b1010100 #
b1010100 .
0!
b1010101 *
1$
#870000
0$
#875000
b1010110 0
b1010101 #
b1010101 .
1!
b1010110 *
1$
#880000
0$
#885000
0+
b1010111 0
b1010110 #
b1010110 .
b1010111 *
1$
#890000
0$
#895000
1,
b1011000 0
b1010111 #
b1010111 .
0!
b1011000 *
1$
#900000
0$
#905000
b1011001 0
b1011000 #
b1011000 .
1!
b1011001 *
1$
#910000
0$
#915000
b1011010 0
b1011001 #
b1011001 .
b1011010 *
1$
#920000
0$
#925000
b1011011 0
b1011010 #
b1011010 .
b1011011 *
1$
#930000
0$
#935000
1+
0,
b1011100 0
b1011011 #
b1011011 .
b1011100 *
1$
#940000
0$
#945000
1,
b1011101 0
b1011100 #
b1011100 .
b1011101 *
1$
#950000
0$
#955000
0+
0,
b1011110 0
b1011101 #
b1011101 .
0!
b1011110 *
1$
#960000
0$
#965000
1+
1,
b1011111 0
b1011110 #
b1011110 .
b1011111 *
1$
#970000
0$
#975000
b1100000 0
b1011111 #
b1011111 .
b1100000 *
1$
#980000
0$
#985000
0+
0,
b1100001 0
b1100000 #
b1100000 .
b1100001 *
1$
#990000
0$
#995000
1+
b1100010 0
b1100001 #
b1100001 .
b1100010 *
1$
#1000000
0$
#1005000
0+
1,
b1100011 0
b1100010 #
b1100010 .
1!
b1100011 *
1$
#1010000
0$
#1015000
1+
b1100100 0
b1100011 #
b1100011 .
b1100100 *
1$
#1020000
0$
#1025000
0,
b1100101 0
b1100100 #
b1100100 .
0!
b1100101 *
1$
#1030000
0$
#1035000
0+
1,
b1100110 0
b1100101 #
b1100101 .
1!
b1100110 *
1$
#1040000
0$
#1045000
b1100111 0
b1100110 #
b1100110 .
b1100111 *
1$
#1050000
0$
#1055000
0,
b1101000 0
b1100111 #
b1100111 .
b1101000 *
1$
#1060000
0$
#1065000
1,
b1101001 0
b1101000 #
b1101000 .
0!
b1101001 *
1$
#1070000
0$
#1075000
1+
b1101010 0
b1101001 #
b1101001 .
1!
b1101010 *
1$
#1080000
0$
#1085000
0,
b1101011 0
b1101010 #
b1101010 .
0!
b1101011 *
1$
#1090000
0$
#1095000
1,
b1101100 0
b1101011 #
b1101011 .
1!
b1101100 *
1$
#1100000
0$
#1105000
0+
0,
b1101101 0
b1101100 #
b1101100 .
0!
b1101101 *
1$
#1110000
0$
#1115000
1+
b1101110 0
b1101101 #
b1101101 .
b1101110 *
1$
#1120000
0$
#1125000
1,
b1101111 0
b1101110 #
b1101110 .
1!
b1101111 *
1$
#1130000
0$
#1135000
b1110000 0
b1101111 #
b1101111 .
0!
b1110000 *
1$
#1140000
0$
#1145000
b1110001 0
b1110000 #
b1110000 .
b1110001 *
1$
#1150000
0$
#1155000
0+
0,
b1110010 0
b1110001 #
b1110001 .
b1110010 *
1$
#1160000
0$
#1165000
1,
b1110011 0
b1110010 #
b1110010 .
b1110011 *
1$
#1170000
0$
#1175000
0,
b1110100 0
b1110011 #
b1110011 .
1!
b1110100 *
1$
#1180000
0$
#1185000
1,
b1110101 0
b1110100 #
b1110100 .
0!
b1110101 *
1$
#1190000
0$
#1195000
b1110110 0
b1110101 #
b1110101 .
1!
b1110110 *
1$
#1200000
0$
#1205000
b1110111 0
b1110110 #
b1110110 .
b1110111 *
1$
#1210000
0$
#1215000
0,
b1111000 0
b1110111 #
b1110111 .
b1111000 *
1$
#1220000
0$
#1225000
1+
1,
b1111001 0
b1111000 #
b1111000 .
0!
b1111001 *
1$
#1230000
0$
#1235000
b1111010 0
b1111001 #
b1111001 .
b1111010 *
1$
#1240000
0$
#1245000
0+
b1111011 0
b1111010 #
b1111010 .
b1111011 *
1$
#1250000
0$
#1255000
1+
0,
b1111100 0
b1111011 #
b1111011 .
1!
b1111100 *
1$
#1260000
0$
#1265000
0+
1,
b1111101 0
b1111100 #
b1111100 .
b1111101 *
1$
#1270000
0$
#1275000
1+
b1111110 0
b1111101 #
b1111101 .
b1111110 *
1$
#1280000
0$
#1285000
0,
b1111111 0
b1111110 #
b1111110 .
0!
b1111111 *
1$
#1290000
0$
#1295000
1,
b10000000 0
b1111111 #
b1111111 .
1!
b10000000 *
1$
#1300000
0$
#1305000
0,
b10000001 0
b10000000 #
b10000000 .
0!
b10000001 *
1$
#1310000
0$
#1315000
1,
b10000010 0
b10000001 #
b10000001 .
1!
b10000010 *
1$
#1320000
0$
#1325000
0+
0,
b10000011 0
b10000010 #
b10000010 .
0!
b10000011 *
1$
#1330000
0$
#1335000
1,
b10000100 0
b10000011 #
b10000011 .
b10000100 *
1$
#1340000
0$
#1345000
b10000101 0
b10000100 #
b10000100 .
1!
b10000101 *
1$
#1350000
0$
#1355000
b10000110 0
b10000101 #
b10000101 .
b10000110 *
1$
#1360000
0$
#1365000
0,
b10000111 0
b10000110 #
b10000110 .
b10000111 *
1$
#1370000
0$
#1375000
1,
b10001000 0
b10000111 #
b10000111 .
0!
b10001000 *
1$
#1380000
0$
#1385000
b10001001 0
b10001000 #
b10001000 .
1!
b10001001 *
1$
#1390000
0$
#1395000
1+
b10001010 0
b10001001 #
b10001001 .
b10001010 *
1$
#1400000
0$
#1405000
0,
b10001011 0
b10001010 #
b10001010 .
0!
b10001011 *
1$
#1410000
0$
#1415000
0+
1,
b10001100 0
b10001011 #
b10001011 .
1!
b10001100 *
1$
#1420000
0$
#1425000
0,
b10001101 0
b10001100 #
b10001100 .
b10001101 *
1$
#1430000
0$
#1435000
1+
b10001110 0
b10001101 #
b10001101 .
0!
b10001110 *
1$
#1440000
0$
#1445000
1,
b10001111 0
b10001110 #
b10001110 .
1!
b10001111 *
1$
#1450000
0$
#1455000
0,
b10010000 0
b10001111 #
b10001111 .
0!
b10010000 *
1$
#1460000
0$
#1465000
b10010001 0
b10010000 #
b10010000 .
1!
b10010001 *
1$
#1470000
0$
#1475000
b10010010 0
b10010001 #
b10010001 .
b10010010 *
1$
#1480000
0$
#1485000
b10010011 0
b10010010 #
b10010010 .
b10010011 *
1$
#1490000
0$
#1495000
1,
b10010100 0
b10010011 #
b10010011 .
b10010100 *
1$
#1500000
0$
#1505000
0+
0,
b10010101 0
b10010100 #
b10010100 .
0!
b10010101 *
1$
#1510000
0$
#1515000
1+
1,
b10010110 0
b10010101 #
b10010101 .
b10010110 *
1$
#1520000
0$
#1525000
b10010111 0
b10010110 #
b10010110 .
b10010111 *
1$
#1530000
0$
#1535000
0+
0,
b10011000 0
b10010111 #
b10010111 .
b10011000 *
1$
#1540000
0$
#1545000
1,
b10011001 0
b10011000 #
b10011000 .
b10011001 *
1$
#1550000
0$
#1555000
0,
b10011010 0
b10011001 #
b10011001 .
1!
b10011010 *
1$
#1560000
0$
#1565000
b10011011 0
b10011010 #
b10011010 .
0!
b10011011 *
1$
#1570000
0$
#1575000
1,
b10011100 0
b10011011 #
b10011011 .
b10011100 *
1$
#1580000
0$
#1585000
0,
b10011101 0
b10011100 #
b10011100 .
1!
b10011101 *
1$
#1590000
0$
#1595000
b10011110 0
b10011101 #
b10011101 .
0!
b10011110 *
1$
#1600000
0$
#1605000
1+
1,
b10011111 0
b10011110 #
b10011110 .
b10011111 *
1$
#1610000
0$
#1615000
0+
b10100000 0
b10011111 #
b10011111 .
b10100000 *
1$
#1620000
0$
#1625000
1+
0,
b10100001 0
b10100000 #
b10100000 .
1!
b10100001 *
1$
#1630000
0$
#1635000
1,
b10100010 0
b10100001 #
b10100001 .
b10100010 *
1$
#1640000
0$
#1645000
0,
b10100011 0
b10100010 #
b10100010 .
0!
b10100011 *
1$
#1650000
0$
#1655000
0+
1,
b10100100 0
b10100011 #
b10100011 .
1!
b10100100 *
1$
#1660000
0$
#1665000
1+
0,
b10100101 0
b10100100 #
b10100100 .
b10100101 *
1$
#1670000
0$
#1675000
b10100110 0
b10100101 #
b10100101 .
b10100110 *
1$
#1680000
0$
#1685000
0+
1,
b10100111 0
b10100110 #
b10100110 .
b10100111 *
1$
#1690000
0$
#1695000
1+
b10101000 0
b10100111 #
b10100111 .
b10101000 *
1$
#1700000
0$
#1705000
b10101001 0
b10101000 #
b10101000 .
0!
b10101001 *
1$
#1710000
0$
#1715000
b10101010 0
b10101001 #
b10101001 .
b10101010 *
1$
#1720000
0$
#1725000
0+
0,
b10101011 0
b10101010 #
b10101010 .
b10101011 *
1$
#1730000
0$
#1735000
1+
b10101100 0
b10101011 #
b10101011 .
b10101100 *
1$
#1740000
0$
#1745000
b10101101 0
b10101100 #
b10101100 .
1!
b10101101 *
1$
#1750000
0$
#1755000
0+
b10101110 0
b10101101 #
b10101101 .
b10101110 *
1$
#1760000
0$
#1765000
1+
1,
b10101111 0
b10101110 #
b10101110 .
0!
b10101111 *
1$
#1770000
0$
#1775000
0+
b10110000 0
b10101111 #
b10101111 .
b10110000 *
1$
#1780000
0$
#1785000
b10110001 0
b10110000 #
b10110000 .
1!
b10110001 *
1$
#1790000
0$
#1795000
b10110010 0
b10110001 #
b10110001 .
b10110010 *
1$
#1800000
0$
#1805000
0,
b10110011 0
b10110010 #
b10110010 .
b10110011 *
1$
#1810000
0$
#1815000
1,
b10110100 0
b10110011 #
b10110011 .
0!
b10110100 *
1$
#1820000
0$
#1825000
1+
0,
b10110101 0
b10110100 #
b10110100 .
1!
b10110101 *
1$
#1830000
0$
#1835000
0+
b10110110 0
b10110101 #
b10110101 .
b10110110 *
1$
#1840000
0$
#1845000
1+
b10110111 0
b10110110 #
b10110110 .
0!
b10110111 *
1$
#1850000
0$
#1855000
b10111000 0
b10110111 #
b10110111 .
1!
b10111000 *
1$
#1860000
0$
#1865000
0+
b10111001 0
b10111000 #
b10111000 .
b10111001 *
1$
#1870000
0$
#1875000
1+
b10111010 0
b10111001 #
b10111001 .
0!
b10111010 *
1$
#1880000
0$
#1885000
b10111011 0
b10111010 #
b10111010 .
1!
b10111011 *
1$
#1890000
0$
#1895000
0+
1,
b10111100 0
b10111011 #
b10111011 .
b10111100 *
1$
#1900000
0$
#1905000
1+
b10111101 0
b10111100 #
b10111100 .
b10111101 *
1$
#1910000
0$
#1915000
b10111110 0
b10111101 #
b10111101 .
0!
b10111110 *
1$
#1920000
0$
#1925000
0+
0,
b10111111 0
b10111110 #
b10111110 .
b10111111 *
1$
#1930000
0$
#1935000
1+
1,
b11000000 0
b10111111 #
b10111111 .
b11000000 *
1$
#1940000
0$
#1945000
0,
b11000001 0
b11000000 #
b11000000 .
b11000001 *
1$
#1950000
0$
#1955000
0+
1,
b11000010 0
b11000001 #
b11000001 .
1!
b11000010 *
1$
#1960000
0$
#1965000
1+
b11000011 0
b11000010 #
b11000010 .
b11000011 *
1$
#1970000
0$
#1975000
0,
b11000100 0
b11000011 #
b11000011 .
0!
b11000100 *
1$
#1980000
0$
#1985000
0+
1,
b11000101 0
b11000100 #
b11000100 .
1!
b11000101 *
1$
#1990000
0$
#1995000
0,
b11000110 0
b11000101 #
b11000101 .
b11000110 *
1$
#2000000
0$
#2005000
1+
1,
b11000111 0
b11000110 #
b11000110 .
0!
b11000111 *
1$
#2010000
0$
#2015000
0,
b11001000 0
b11000111 #
b11000111 .
b11001000 *
1$
#2020000
0$
#2025000
0+
1,
b11001001 0
b11001000 #
b11001000 .
1!
b11001001 *
1$
#2030000
0$
#2035000
1+
b11001010 0
b11001001 #
b11001001 .
b11001010 *
1$
#2040000
0$
#2045000
0+
0,
b11001011 0
b11001010 #
b11001010 .
0!
b11001011 *
1$
#2050000
0$
#2055000
b11001100 0
b11001011 #
b11001011 .
b11001100 *
1$
#2060000
0$
#2065000
1+
b11001101 0
b11001100 #
b11001100 .
b11001101 *
1$
#2070000
0$
#2075000
0+
1,
b11001110 0
b11001101 #
b11001101 .
1!
b11001110 *
1$
#2080000
0$
#2085000
1+
b11001111 0
b11001110 #
b11001110 .
b11001111 *
1$
#2090000
0$
#2095000
0+
0,
b11010000 0
b11001111 #
b11001111 .
0!
b11010000 *
1$
#2100000
0$
#2105000
1+
1,
b11010001 0
b11010000 #
b11010000 .
1!
b11010001 *
1$
#2110000
0$
#2115000
0+
0,
b11010010 0
b11010001 #
b11010001 .
b11010010 *
1$
#2120000
0$
#2125000
b11010011 0
b11010010 #
b11010010 .
0!
b11010011 *
1$
#2130000
0$
#2135000
1+
b11010100 0
b11010011 #
b11010011 .
1!
b11010100 *
1$
#2140000
0$
#2145000
1,
b11010101 0
b11010100 #
b11010100 .
0!
b11010101 *
1$
#2150000
0$
#2155000
0,
b11010110 0
b11010101 #
b11010101 .
b11010110 *
1$
#2160000
0$
#2165000
0+
b11010111 0
b11010110 #
b11010110 .
1!
b11010111 *
1$
#2170000
0$
#2175000
1+
b11011000 0
b11010111 #
b11010111 .
0!
b11011000 *
1$
#2180000
0$
#2185000
1,
b11011001 0
b11011000 #
b11011000 .
1!
b11011001 *
1$
#2190000
0$
#2195000
0+
b11011010 0
b11011001 #
b11011001 .
0!
b11011010 *
1$
#2200000
0$
#2205000
1+
b11011011 0
b11011010 #
b11011010 .
1!
b11011011 *
1$
#2210000
0$
#2215000
0,
b11011100 0
b11011011 #
b11011011 .
0!
b11011100 *
1$
#2220000
0$
#2225000
b11011101 0
b11011100 #
b11011100 .
1!
b11011101 *
1$
#2230000
0$
#2235000
1,
b11011110 0
b11011101 #
b11011101 .
b11011110 *
1$
#2240000
0$
#2245000
0+
b11011111 0
b11011110 #
b11011110 .
0!
b11011111 *
1$
#2250000
0$
#2255000
1+
b11100000 0
b11011111 #
b11011111 .
1!
b11100000 *
1$
#2260000
0$
#2265000
b11100001 0
b11100000 #
b11100000 .
0!
b11100001 *
1$
#2270000
0$
#2275000
b11100010 0
b11100001 #
b11100001 .
b11100010 *
1$
#2280000
0$
#2285000
0,
b11100011 0
b11100010 #
b11100010 .
b11100011 *
1$
#2290000
0$
#2295000
0+
b11100100 0
b11100011 #
b11100011 .
1!
b11100100 *
1$
#2300000
0$
#2305000
1+
1,
b11100101 0
b11100100 #
b11100100 .
0!
b11100101 *
1$
#2310000
0$
#2315000
0+
b11100110 0
b11100101 #
b11100101 .
b11100110 *
1$
#2320000
0$
#2325000
b11100111 0
b11100110 #
b11100110 .
1!
b11100111 *
1$
#2330000
0$
#2335000
0,
b11101000 0
b11100111 #
b11100111 .
b11101000 *
1$
#2340000
0$
#2345000
1+
b11101001 0
b11101000 #
b11101000 .
0!
b11101001 *
1$
#2350000
0$
#2355000
0+
1,
b11101010 0
b11101001 #
b11101001 .
1!
b11101010 *
1$
#2360000
0$
#2365000
1+
b11101011 0
b11101010 #
b11101010 .
b11101011 *
1$
#2370000
0$
#2375000
0+
b11101100 0
b11101011 #
b11101011 .
0!
b11101100 *
1$
#2380000
0$
#2385000
b11101101 0
b11101100 #
b11101100 .
1!
b11101101 *
1$
#2390000
0$
#2395000
0,
b11101110 0
b11101101 #
b11101101 .
b11101110 *
1$
#2400000
0$
#2405000
1+
1,
b11101111 0
b11101110 #
b11101110 .
0!
b11101111 *
1$
#2410000
0$
#2415000
0+
b11110000 0
b11101111 #
b11101111 .
b11110000 *
1$
#2420000
0$
#2425000
0,
b11110001 0
b11110000 #
b11110000 .
1!
b11110001 *
1$
#2430000
0$
#2435000
1+
1,
b11110010 0
b11110001 #
b11110001 .
0!
b11110010 *
1$
#2440000
0$
#2445000
0,
b11110011 0
b11110010 #
b11110010 .
b11110011 *
1$
#2450000
0$
#2455000
b11110100 0
b11110011 #
b11110011 .
1!
b11110100 *
1$
#2460000
0$
#2465000
0+
b11110101 0
b11110100 #
b11110100 .
b11110101 *
1$
#2470000
0$
#2475000
b11110110 0
b11110101 #
b11110101 .
0!
b11110110 *
1$
#2480000
0$
#2485000
1+
1,
b11110111 0
b11110110 #
b11110110 .
b11110111 *
1$
#2490000
0$
#2495000
b11111000 0
b11110111 #
b11110111 .
b11111000 *
1$
#2500000
0$
#2505000
0,
b11111001 0
b11111000 #
b11111000 .
b11111001 *
1$
#2510000
0$
#2515000
0+
1,
b11111010 0
b11111001 #
b11111001 .
1!
b11111010 *
1$
#2520000
0$
#2525000
1+
b11111011 0
b11111010 #
b11111010 .
b11111011 *
1$
#2530000
0$
#2535000
b11111100 0
b11111011 #
b11111011 .
0!
b11111100 *
1$
#2540000
0$
#2545000
0+
b11111101 0
b11111100 #
b11111100 .
b11111101 *
1$
#2550000
0$
#2555000
1+
0,
b11111110 0
b11111101 #
b11111101 .
1!
b11111110 *
1$
#2560000
0$
#2565000
1,
b11111111 0
b11111110 #
b11111110 .
b11111111 *
1$
#2570000
0$
#2575000
b100000000 0
b11111111 #
b11111111 .
0!
b100000000 *
1$
#2580000
0$
#2585000
b100000001 0
b100000000 #
b100000000 .
b100000001 *
1$
#2590000
0$
#2595000
b100000010 0
b100000001 #
b100000001 .
b100000010 *
1$
#2600000
0$
#2605000
0,
b100000011 0
b100000010 #
b100000010 .
b100000011 *
1$
#2610000
0$
#2615000
1,
b100000100 0
b100000011 #
b100000011 .
1!
b100000100 *
1$
#2620000
0$
#2625000
0+
0,
b100000101 0
b100000100 #
b100000100 .
0!
b100000101 *
1$
#2630000
0$
#2635000
1,
b100000110 0
b100000101 #
b100000101 .
b100000110 *
1$
#2640000
0$
#2645000
1+
b100000111 0
b100000110 #
b100000110 .
1!
b100000111 *
1$
#2650000
0$
#2655000
0+
b100001000 0
b100000111 #
b100000111 .
0!
b100001000 *
1$
#2660000
0$
#2665000
0,
b100001001 0
b100001000 #
b100001000 .
1!
b100001001 *
1$
#2670000
0$
#2675000
1,
b100001010 0
b100001001 #
b100001001 .
0!
b100001010 *
1$
#2680000
0$
#2685000
b100001011 0
b100001010 #
b100001010 .
1!
b100001011 *
1$
#2690000
0$
#2695000
b100001100 0
b100001011 #
b100001011 .
b100001100 *
1$
#2700000
0$
